{
  "Human": {
    "DisplayName": "человек",
    "Enabled": true,
    "ModActive": true,
    "BasePrice": 1000,
    "MinAge": 15,
    "MaxAge": 45,
    "AllowCustomXenotypes": true,
    "DefaultXenotype": "Baseliner",
    "PreferredPawnKindDefName": null,
    "AllowedGenders": {
      "AllowMale": true,
      "AllowFemale": true,
      "AllowOther": true
    },
    "XenotypePrices": {
      "Baseliner": 1000.0,
      "Dirtmole": 1000.0,
      "Genie": 1200.0,
      "Hussar": 1750.0,
      "Sanguophage": 5000.0,
      "Neanderthal": 1000.0,
      "Pigskin": 1000.0,
      "Impid": 2000.0,
      "Waster": 1750.0,
      "Yttakin": 1000.0,
      "Highmate": 1000.0,
      "Starjack": 1750.0
    },
    "EnabledXenotypes": {
      "Baseliner": true,
      "Dirtmole": true,
      "Genie": true,
      "Hussar": true,
      "Sanguophage": false,
      "Neanderthal": true,
      "Pigskin": true,
      "Impid": true,
      "Waster": true,
      "Yttakin": true,
      "Highmate": true,
      "Starjack": true
    }
  },
  "OG_Abhuman_Beastman": {
    "DisplayName": "beastman",
    "Enabled": true,
    "ModActive": false,
    "BasePrice": 1750,
    "MinAge": 16,
    "MaxAge": 65,
    "AllowCustomXenotypes": true,
    "DefaultXenotype": "Baseliner",
    "PreferredPawnKindDefName": null,
    "AllowedGenders": {
      "AllowMale": true,
      "AllowFemale": true,
      "AllowOther": true
    },
    "XenotypePrices": {
      "Baseliner": 1750.0,
      "Dirtmole": 1750.0,
      "Genie": 1750.0,
      "Hussar": 2187.5,
      "Sanguophage": 5687.5,
      "Neanderthal": 1750.0,
      "Pigskin": 1750.0,
      "Impid": 2625.0,
      "Waster": 2187.5,
      "Yttakin": 1750.0,
      "Highmate": 1750.0,
      "Starjack": 1750.0,
      "EMCM_HereticAstartes": 1750.0,
      "EMCM_HereticAstartes_Khorne": 1750.0,
      "EMCM_HereticAstartes_WorldEaters": 1750.0,
      "EMCM_HereticAstartes_Nurgle": 1750.0,
      "EMCM_HereticAstartes_DeathGuard": 1750.0,
      "EMCM_HereticAstartes_Tzeentch": 1750.0,
      "EMCM_HereticAstartes_ThousandSons": 1750.0,
      "EMCM_HereticAstartes_Slaanesh": 1750.0,
      "EMCM_HereticAstartes_EmperorsChildren": 1750.0,
      "EMCM_HereticAstartes_Undivided": 1750.0,
      "EMCM_HereticAstartes_FallenAngels": 1750.0,
      "EMCM_HereticAstartes_NightLords": 1750.0,
      "EMSM_Astartes": 1750.0,
      "EMSM_Astartes_Salamanders": 1750.0,
      "EMSM_Astartes_ImperialFists": 1750.0,
      "EMSM_Astartes_IronHands": 1750.0,
      "EMSM_Astartes_BlackTemplars": 1750.0,
      "EMSM_Astartes_CrimsonFists": 1750.0,
      "EMSM_Astartes_RavenGuard": 1750.0,
      "EMSM_Astartes_SpaceWolves": 1750.0,
      "EMSM_Astartes_LongFang": 1750.0,
      "EMSM_Astartes_Wulfen": 1750.0,
      "EMSM_Astartes_WhiteScars": 1750.0,
      "EMCH_Poxwalker": 1750.0,
      "EMNC_Necrons": 1750.0,
      "EMOK_Orkz_Grot": 2187.5,
      "EMOK_Orkz_Boyz": 2625.0,
      "EMOK_Orkz_Mek": 2625.0,
      "EMOK_Orkz_Painboy": 2625.0,
      "EMOK_Orkz_Runtherd": 2625.0,
      "EMOK_Orkz_Weirdboy": 2625.0,
      "EMOK_Orkz_Kommando": 2625.0,
      "EMOK_Orkz_Warboss": 2625.0,
      "EMGC_BroodBrothers": 2187.5,
      "EMGC_AcolyteHybrids": 2187.5,
      "EMGC_AcolyteIconward": 5687.5,
      "EMGC_Aberrant": 2625.0,
      "EMGC_AberrantHypermorph": 2625.0,
      "EMGC_NeophyteHybrids": 2187.5,
      "EMGC_Magus": 8750.0,
      "EMGC_PurestrainGenestealer": 9625.0,
      "EMGC_Patriarch": 9187.5,
      "EMAE_Asuryani": 1750.0,
      "EMAE_Exodites": 1750.0,
      "EMTS_Tzaangor": 1750.0,
      "EMTS_TzaangorEnlightened": 1750.0,
      "EMTS_TzaangorShaman": 2625.0
    },
    "EnabledXenotypes": {
      "Baseliner": true,
      "Dirtmole": true,
      "Genie": true,
      "Hussar": true,
      "Sanguophage": true,
      "Neanderthal": true,
      "Pigskin": true,
      "Impid": true,
      "Waster": true,
      "Yttakin": true,
      "Highmate": true,
      "Starjack": true,
      "EMCM_HereticAstartes": true,
      "EMCM_HereticAstartes_Khorne": true,
      "EMCM_HereticAstartes_WorldEaters": true,
      "EMCM_HereticAstartes_Nurgle": true,
      "EMCM_HereticAstartes_DeathGuard": true,
      "EMCM_HereticAstartes_Tzeentch": true,
      "EMCM_HereticAstartes_ThousandSons": true,
      "EMCM_HereticAstartes_Slaanesh": true,
      "EMCM_HereticAstartes_EmperorsChildren": true,
      "EMCM_HereticAstartes_Undivided": true,
      "EMCM_HereticAstartes_FallenAngels": true,
      "EMCM_HereticAstartes_NightLords": true,
      "EMSM_Astartes": true,
      "EMSM_Astartes_Salamanders": true,
      "EMSM_Astartes_ImperialFists": true,
      "EMSM_Astartes_IronHands": true,
      "EMSM_Astartes_BlackTemplars": true,
      "EMSM_Astartes_CrimsonFists": true,
      "EMSM_Astartes_RavenGuard": true,
      "EMSM_Astartes_SpaceWolves": true,
      "EMSM_Astartes_LongFang": true,
      "EMSM_Astartes_Wulfen": true,
      "EMSM_Astartes_WhiteScars": true,
      "EMCH_Poxwalker": true,
      "EMNC_Necrons": true,
      "EMOK_Orkz_Grot": true,
      "EMOK_Orkz_Boyz": true,
      "EMOK_Orkz_Mek": true,
      "EMOK_Orkz_Painboy": true,
      "EMOK_Orkz_Runtherd": true,
      "EMOK_Orkz_Weirdboy": true,
      "EMOK_Orkz_Kommando": true,
      "EMOK_Orkz_Warboss": true,
      "EMGC_BroodBrothers": true,
      "EMGC_AcolyteHybrids": true,
      "EMGC_AcolyteIconward": true,
      "EMGC_Aberrant": true,
      "EMGC_AberrantHypermorph": true,
      "EMGC_NeophyteHybrids": true,
      "EMGC_Magus": true,
      "EMGC_PurestrainGenestealer": true,
      "EMGC_Patriarch": true,
      "EMAE_Asuryani": true,
      "EMAE_Exodites": true,
      "EMTS_Tzaangor": true,
      "EMTS_TzaangorEnlightened": true,
      "EMTS_TzaangorShaman": true
    }
  },
  "OG_Human_Mechanicus": {
    "DisplayName": "human (Mechanicus)",
    "Enabled": true,
    "ModActive": false,
    "BasePrice": 1750,
    "MinAge": 16,
    "MaxAge": 65,
    "AllowCustomXenotypes": true,
    "DefaultXenotype": "Baseliner",
    "PreferredPawnKindDefName": null,
    "AllowedGenders": {
      "AllowMale": true,
      "AllowFemale": true,
      "AllowOther": true
    },
    "XenotypePrices": {
      "Baseliner": 1750.0,
      "Dirtmole": 1750.0,
      "Genie": 1750.0,
      "Hussar": 2187.5,
      "Sanguophage": 5687.5,
      "Neanderthal": 1750.0,
      "Pigskin": 1750.0,
      "Impid": 2625.0,
      "Waster": 2187.5,
      "Yttakin": 1750.0,
      "Highmate": 1750.0,
      "Starjack": 1750.0,
      "EMCM_HereticAstartes": 1750.0,
      "EMCM_HereticAstartes_Khorne": 1750.0,
      "EMCM_HereticAstartes_WorldEaters": 1750.0,
      "EMCM_HereticAstartes_Nurgle": 1750.0,
      "EMCM_HereticAstartes_DeathGuard": 1750.0,
      "EMCM_HereticAstartes_Tzeentch": 1750.0,
      "EMCM_HereticAstartes_ThousandSons": 1750.0,
      "EMCM_HereticAstartes_Slaanesh": 1750.0,
      "EMCM_HereticAstartes_EmperorsChildren": 1750.0,
      "EMCM_HereticAstartes_Undivided": 1750.0,
      "EMCM_HereticAstartes_FallenAngels": 1750.0,
      "EMCM_HereticAstartes_NightLords": 1750.0,
      "EMSM_Astartes": 1750.0,
      "EMSM_Astartes_Salamanders": 1750.0,
      "EMSM_Astartes_ImperialFists": 1750.0,
      "EMSM_Astartes_IronHands": 1750.0,
      "EMSM_Astartes_BlackTemplars": 1750.0,
      "EMSM_Astartes_CrimsonFists": 1750.0,
      "EMSM_Astartes_RavenGuard": 1750.0,
      "EMSM_Astartes_SpaceWolves": 1750.0,
      "EMSM_Astartes_LongFang": 1750.0,
      "EMSM_Astartes_Wulfen": 1750.0,
      "EMSM_Astartes_WhiteScars": 1750.0,
      "EMCH_Poxwalker": 1750.0,
      "EMNC_Necrons": 1750.0,
      "EMOK_Orkz_Grot": 2187.5,
      "EMOK_Orkz_Boyz": 2625.0,
      "EMOK_Orkz_Mek": 2625.0,
      "EMOK_Orkz_Painboy": 2625.0,
      "EMOK_Orkz_Runtherd": 2625.0,
      "EMOK_Orkz_Weirdboy": 2625.0,
      "EMOK_Orkz_Kommando": 2625.0,
      "EMOK_Orkz_Warboss": 2625.0,
      "EMGC_BroodBrothers": 2187.5,
      "EMGC_AcolyteHybrids": 2187.5,
      "EMGC_AcolyteIconward": 5687.5,
      "EMGC_Aberrant": 2625.0,
      "EMGC_AberrantHypermorph": 2625.0,
      "EMGC_NeophyteHybrids": 2187.5,
      "EMGC_Magus": 8750.0,
      "EMGC_PurestrainGenestealer": 9625.0,
      "EMGC_Patriarch": 9187.5,
      "EMAE_Asuryani": 1750.0,
      "EMAE_Exodites": 1750.0,
      "EMTS_Tzaangor": 1750.0,
      "EMTS_TzaangorEnlightened": 1750.0,
      "EMTS_TzaangorShaman": 2625.0
    },
    "EnabledXenotypes": {
      "Baseliner": true,
      "Dirtmole": true,
      "Genie": true,
      "Hussar": true,
      "Sanguophage": true,
      "Neanderthal": true,
      "Pigskin": true,
      "Impid": true,
      "Waster": true,
      "Yttakin": true,
      "Highmate": true,
      "Starjack": true,
      "EMCM_HereticAstartes": true,
      "EMCM_HereticAstartes_Khorne": true,
      "EMCM_HereticAstartes_WorldEaters": true,
      "EMCM_HereticAstartes_Nurgle": true,
      "EMCM_HereticAstartes_DeathGuard": true,
      "EMCM_HereticAstartes_Tzeentch": true,
      "EMCM_HereticAstartes_ThousandSons": true,
      "EMCM_HereticAstartes_Slaanesh": true,
      "EMCM_HereticAstartes_EmperorsChildren": true,
      "EMCM_HereticAstartes_Undivided": true,
      "EMCM_HereticAstartes_FallenAngels": true,
      "EMCM_HereticAstartes_NightLords": true,
      "EMSM_Astartes": true,
      "EMSM_Astartes_Salamanders": true,
      "EMSM_Astartes_ImperialFists": true,
      "EMSM_Astartes_IronHands": true,
      "EMSM_Astartes_BlackTemplars": true,
      "EMSM_Astartes_CrimsonFists": true,
      "EMSM_Astartes_RavenGuard": true,
      "EMSM_Astartes_SpaceWolves": true,
      "EMSM_Astartes_LongFang": true,
      "EMSM_Astartes_Wulfen": true,
      "EMSM_Astartes_WhiteScars": true,
      "EMCH_Poxwalker": true,
      "EMNC_Necrons": true,
      "EMOK_Orkz_Grot": true,
      "EMOK_Orkz_Boyz": true,
      "EMOK_Orkz_Mek": true,
      "EMOK_Orkz_Painboy": true,
      "EMOK_Orkz_Runtherd": true,
      "EMOK_Orkz_Weirdboy": true,
      "EMOK_Orkz_Kommando": true,
      "EMOK_Orkz_Warboss": true,
      "EMGC_BroodBrothers": true,
      "EMGC_AcolyteHybrids": true,
      "EMGC_AcolyteIconward": true,
      "EMGC_Aberrant": true,
      "EMGC_AberrantHypermorph": true,
      "EMGC_NeophyteHybrids": true,
      "EMGC_Magus": true,
      "EMGC_PurestrainGenestealer": true,
      "EMGC_Patriarch": true,
      "EMAE_Asuryani": true,
      "EMAE_Exodites": true,
      "EMTS_Tzaangor": true,
      "EMTS_TzaangorEnlightened": true,
      "EMTS_TzaangorShaman": true
    }
  },
  "OG_Abhuman_Ogryn": {
    "DisplayName": "ogryn",
    "Enabled": true,
    "ModActive": false,
    "BasePrice": 2500,
    "MinAge": 16,
    "MaxAge": 65,
    "AllowCustomXenotypes": true,
    "DefaultXenotype": "Baseliner",
    "PreferredPawnKindDefName": null,
    "AllowedGenders": {
      "AllowMale": true,
      "AllowFemale": true,
      "AllowOther": true
    },
    "XenotypePrices": {
      "Baseliner": 2500.0,
      "Dirtmole": 2500.0,
      "Genie": 2500.0,
      "Hussar": 3125.0,
      "Sanguophage": 8125.0,
      "Neanderthal": 2500.0,
      "Pigskin": 2500.0,
      "Impid": 3750.0,
      "Waster": 3125.0,
      "Yttakin": 2500.0,
      "Highmate": 2500.0,
      "Starjack": 2500.0,
      "EMCM_HereticAstartes": 2500.0,
      "EMCM_HereticAstartes_Khorne": 2500.0,
      "EMCM_HereticAstartes_WorldEaters": 2500.0,
      "EMCM_HereticAstartes_Nurgle": 2500.0,
      "EMCM_HereticAstartes_DeathGuard": 2500.0,
      "EMCM_HereticAstartes_Tzeentch": 2500.0,
      "EMCM_HereticAstartes_ThousandSons": 2500.0,
      "EMCM_HereticAstartes_Slaanesh": 2500.0,
      "EMCM_HereticAstartes_EmperorsChildren": 2500.0,
      "EMCM_HereticAstartes_Undivided": 2500.0,
      "EMCM_HereticAstartes_FallenAngels": 2500.0,
      "EMCM_HereticAstartes_NightLords": 2500.0,
      "EMSM_Astartes": 2500.0,
      "EMSM_Astartes_Salamanders": 2500.0,
      "EMSM_Astartes_ImperialFists": 2500.0,
      "EMSM_Astartes_IronHands": 2500.0,
      "EMSM_Astartes_BlackTemplars": 2500.0,
      "EMSM_Astartes_CrimsonFists": 2500.0,
      "EMSM_Astartes_RavenGuard": 2500.0,
      "EMSM_Astartes_SpaceWolves": 2500.0,
      "EMSM_Astartes_LongFang": 2500.0,
      "EMSM_Astartes_Wulfen": 2500.0,
      "EMSM_Astartes_WhiteScars": 2500.0,
      "EMCH_Poxwalker": 2500.0,
      "EMNC_Necrons": 2500.0,
      "EMOK_Orkz_Grot": 3125.0,
      "EMOK_Orkz_Boyz": 3750.0,
      "EMOK_Orkz_Mek": 3750.0,
      "EMOK_Orkz_Painboy": 3750.0,
      "EMOK_Orkz_Runtherd": 3750.0,
      "EMOK_Orkz_Weirdboy": 3750.0,
      "EMOK_Orkz_Kommando": 3750.0,
      "EMOK_Orkz_Warboss": 3750.0,
      "EMGC_BroodBrothers": 3125.0,
      "EMGC_AcolyteHybrids": 3125.0,
      "EMGC_AcolyteIconward": 8125.0,
      "EMGC_Aberrant": 3750.0,
      "EMGC_AberrantHypermorph": 3750.0,
      "EMGC_NeophyteHybrids": 3125.0,
      "EMGC_Magus": 12500.0,
      "EMGC_PurestrainGenestealer": 13750.0,
      "EMGC_Patriarch": 13125.0,
      "EMAE_Asuryani": 2500.0,
      "EMAE_Exodites": 2500.0,
      "EMTS_Tzaangor": 2500.0,
      "EMTS_TzaangorEnlightened": 2500.0,
      "EMTS_TzaangorShaman": 3750.0
    },
    "EnabledXenotypes": {
      "Baseliner": true,
      "Dirtmole": true,
      "Genie": true,
      "Hussar": true,
      "Sanguophage": true,
      "Neanderthal": true,
      "Pigskin": true,
      "Impid": true,
      "Waster": true,
      "Yttakin": true,
      "Highmate": true,
      "Starjack": true,
      "EMCM_HereticAstartes": true,
      "EMCM_HereticAstartes_Khorne": true,
      "EMCM_HereticAstartes_WorldEaters": true,
      "EMCM_HereticAstartes_Nurgle": true,
      "EMCM_HereticAstartes_DeathGuard": true,
      "EMCM_HereticAstartes_Tzeentch": true,
      "EMCM_HereticAstartes_ThousandSons": true,
      "EMCM_HereticAstartes_Slaanesh": true,
      "EMCM_HereticAstartes_EmperorsChildren": true,
      "EMCM_HereticAstartes_Undivided": true,
      "EMCM_HereticAstartes_FallenAngels": true,
      "EMCM_HereticAstartes_NightLords": true,
      "EMSM_Astartes": true,
      "EMSM_Astartes_Salamanders": true,
      "EMSM_Astartes_ImperialFists": true,
      "EMSM_Astartes_IronHands": true,
      "EMSM_Astartes_BlackTemplars": true,
      "EMSM_Astartes_CrimsonFists": true,
      "EMSM_Astartes_RavenGuard": true,
      "EMSM_Astartes_SpaceWolves": true,
      "EMSM_Astartes_LongFang": true,
      "EMSM_Astartes_Wulfen": true,
      "EMSM_Astartes_WhiteScars": true,
      "EMCH_Poxwalker": true,
      "EMNC_Necrons": true,
      "EMOK_Orkz_Grot": true,
      "EMOK_Orkz_Boyz": true,
      "EMOK_Orkz_Mek": true,
      "EMOK_Orkz_Painboy": true,
      "EMOK_Orkz_Runtherd": true,
      "EMOK_Orkz_Weirdboy": true,
      "EMOK_Orkz_Kommando": true,
      "EMOK_Orkz_Warboss": true,
      "EMGC_BroodBrothers": true,
      "EMGC_AcolyteHybrids": true,
      "EMGC_AcolyteIconward": true,
      "EMGC_Aberrant": true,
      "EMGC_AberrantHypermorph": true,
      "EMGC_NeophyteHybrids": true,
      "EMGC_Magus": true,
      "EMGC_PurestrainGenestealer": true,
      "EMGC_Patriarch": true,
      "EMAE_Asuryani": true,
      "EMAE_Exodites": true,
      "EMTS_Tzaangor": true,
      "EMTS_TzaangorEnlightened": true,
      "EMTS_TzaangorShaman": true
    }
  },
  "OG_Abhuman_Ratlin": {
    "DisplayName": "ratling",
    "Enabled": true,
    "ModActive": false,
    "BasePrice": 1750,
    "MinAge": 16,
    "MaxAge": 65,
    "AllowCustomXenotypes": true,
    "DefaultXenotype": "Baseliner",
    "PreferredPawnKindDefName": null,
    "AllowedGenders": {
      "AllowMale": true,
      "AllowFemale": true,
      "AllowOther": true
    },
    "XenotypePrices": {
      "Baseliner": 1750.0,
      "Dirtmole": 1750.0,
      "Genie": 1750.0,
      "Hussar": 2187.5,
      "Sanguophage": 5687.5,
      "Neanderthal": 1750.0,
      "Pigskin": 1750.0,
      "Impid": 2625.0,
      "Waster": 2187.5,
      "Yttakin": 1750.0,
      "Highmate": 1750.0,
      "Starjack": 1750.0,
      "EMCM_HereticAstartes": 1750.0,
      "EMCM_HereticAstartes_Khorne": 1750.0,
      "EMCM_HereticAstartes_WorldEaters": 1750.0,
      "EMCM_HereticAstartes_Nurgle": 1750.0,
      "EMCM_HereticAstartes_DeathGuard": 1750.0,
      "EMCM_HereticAstartes_Tzeentch": 1750.0,
      "EMCM_HereticAstartes_ThousandSons": 1750.0,
      "EMCM_HereticAstartes_Slaanesh": 1750.0,
      "EMCM_HereticAstartes_EmperorsChildren": 1750.0,
      "EMCM_HereticAstartes_Undivided": 1750.0,
      "EMCM_HereticAstartes_FallenAngels": 1750.0,
      "EMCM_HereticAstartes_NightLords": 1750.0,
      "EMSM_Astartes": 1750.0,
      "EMSM_Astartes_Salamanders": 1750.0,
      "EMSM_Astartes_ImperialFists": 1750.0,
      "EMSM_Astartes_IronHands": 1750.0,
      "EMSM_Astartes_BlackTemplars": 1750.0,
      "EMSM_Astartes_CrimsonFists": 1750.0,
      "EMSM_Astartes_RavenGuard": 1750.0,
      "EMSM_Astartes_SpaceWolves": 1750.0,
      "EMSM_Astartes_LongFang": 1750.0,
      "EMSM_Astartes_Wulfen": 1750.0,
      "EMSM_Astartes_WhiteScars": 1750.0,
      "EMCH_Poxwalker": 1750.0,
      "EMNC_Necrons": 1750.0,
      "EMOK_Orkz_Grot": 2187.5,
      "EMOK_Orkz_Boyz": 2625.0,
      "EMOK_Orkz_Mek": 2625.0,
      "EMOK_Orkz_Painboy": 2625.0,
      "EMOK_Orkz_Runtherd": 2625.0,
      "EMOK_Orkz_Weirdboy": 2625.0,
      "EMOK_Orkz_Kommando": 2625.0,
      "EMOK_Orkz_Warboss": 2625.0,
      "EMGC_BroodBrothers": 2187.5,
      "EMGC_AcolyteHybrids": 2187.5,
      "EMGC_AcolyteIconward": 5687.5,
      "EMGC_Aberrant": 2625.0,
      "EMGC_AberrantHypermorph": 2625.0,
      "EMGC_NeophyteHybrids": 2187.5,
      "EMGC_Magus": 8750.0,
      "EMGC_PurestrainGenestealer": 9625.0,
      "EMGC_Patriarch": 9187.5,
      "EMAE_Asuryani": 1750.0,
      "EMAE_Exodites": 1750.0,
      "EMTS_Tzaangor": 1750.0,
      "EMTS_TzaangorEnlightened": 1750.0,
      "EMTS_TzaangorShaman": 2625.0
    },
    "EnabledXenotypes": {
      "Baseliner": true,
      "Dirtmole": true,
      "Genie": true,
      "Hussar": true,
      "Sanguophage": true,
      "Neanderthal": true,
      "Pigskin": true,
      "Impid": true,
      "Waster": true,
      "Yttakin": true,
      "Highmate": true,
      "Starjack": true,
      "EMCM_HereticAstartes": true,
      "EMCM_HereticAstartes_Khorne": true,
      "EMCM_HereticAstartes_WorldEaters": true,
      "EMCM_HereticAstartes_Nurgle": true,
      "EMCM_HereticAstartes_DeathGuard": true,
      "EMCM_HereticAstartes_Tzeentch": true,
      "EMCM_HereticAstartes_ThousandSons": true,
      "EMCM_HereticAstartes_Slaanesh": true,
      "EMCM_HereticAstartes_EmperorsChildren": true,
      "EMCM_HereticAstartes_Undivided": true,
      "EMCM_HereticAstartes_FallenAngels": true,
      "EMCM_HereticAstartes_NightLords": true,
      "EMSM_Astartes": true,
      "EMSM_Astartes_Salamanders": true,
      "EMSM_Astartes_ImperialFists": true,
      "EMSM_Astartes_IronHands": true,
      "EMSM_Astartes_BlackTemplars": true,
      "EMSM_Astartes_CrimsonFists": true,
      "EMSM_Astartes_RavenGuard": true,
      "EMSM_Astartes_SpaceWolves": true,
      "EMSM_Astartes_LongFang": true,
      "EMSM_Astartes_Wulfen": true,
      "EMSM_Astartes_WhiteScars": true,
      "EMCH_Poxwalker": true,
      "EMNC_Necrons": true,
      "EMOK_Orkz_Grot": true,
      "EMOK_Orkz_Boyz": true,
      "EMOK_Orkz_Mek": true,
      "EMOK_Orkz_Painboy": true,
      "EMOK_Orkz_Runtherd": true,
      "EMOK_Orkz_Weirdboy": true,
      "EMOK_Orkz_Kommando": true,
      "EMOK_Orkz_Warboss": true,
      "EMGC_BroodBrothers": true,
      "EMGC_AcolyteHybrids": true,
      "EMGC_AcolyteIconward": true,
      "EMGC_Aberrant": true,
      "EMGC_AberrantHypermorph": true,
      "EMGC_NeophyteHybrids": true,
      "EMGC_Magus": true,
      "EMGC_PurestrainGenestealer": true,
      "EMGC_Patriarch": true,
      "EMAE_Asuryani": true,
      "EMAE_Exodites": true,
      "EMTS_Tzaangor": true,
      "EMTS_TzaangorEnlightened": true,
      "EMTS_TzaangorShaman": true
    }
  },
  "OG_Alien_Tau": {
    "DisplayName": "Tau",
    "Enabled": true,
    "ModActive": false,
    "BasePrice": 1750,
    "MinAge": 16,
    "MaxAge": 65,
    "AllowCustomXenotypes": true,
    "DefaultXenotype": "Baseliner",
    "PreferredPawnKindDefName": null,
    "AllowedGenders": {
      "AllowMale": true,
      "AllowFemale": true,
      "AllowOther": true
    },
    "XenotypePrices": {
      "Baseliner": 1750.0,
      "Dirtmole": 1750.0,
      "Genie": 1750.0,
      "Hussar": 2187.5,
      "Sanguophage": 5687.5,
      "Neanderthal": 1750.0,
      "Pigskin": 1750.0,
      "Impid": 2625.0,
      "Waster": 2187.5,
      "Yttakin": 1750.0,
      "Highmate": 1750.0,
      "Starjack": 1750.0,
      "EMCM_HereticAstartes": 1750.0,
      "EMCM_HereticAstartes_Khorne": 1750.0,
      "EMCM_HereticAstartes_WorldEaters": 1750.0,
      "EMCM_HereticAstartes_Nurgle": 1750.0,
      "EMCM_HereticAstartes_DeathGuard": 1750.0,
      "EMCM_HereticAstartes_Tzeentch": 1750.0,
      "EMCM_HereticAstartes_ThousandSons": 1750.0,
      "EMCM_HereticAstartes_Slaanesh": 1750.0,
      "EMCM_HereticAstartes_EmperorsChildren": 1750.0,
      "EMCM_HereticAstartes_Undivided": 1750.0,
      "EMCM_HereticAstartes_FallenAngels": 1750.0,
      "EMCM_HereticAstartes_NightLords": 1750.0,
      "EMSM_Astartes": 1750.0,
      "EMSM_Astartes_Salamanders": 1750.0,
      "EMSM_Astartes_ImperialFists": 1750.0,
      "EMSM_Astartes_IronHands": 1750.0,
      "EMSM_Astartes_BlackTemplars": 1750.0,
      "EMSM_Astartes_CrimsonFists": 1750.0,
      "EMSM_Astartes_RavenGuard": 1750.0,
      "EMSM_Astartes_SpaceWolves": 1750.0,
      "EMSM_Astartes_LongFang": 1750.0,
      "EMSM_Astartes_Wulfen": 1750.0,
      "EMSM_Astartes_WhiteScars": 1750.0,
      "EMCH_Poxwalker": 1750.0,
      "EMNC_Necrons": 1750.0,
      "EMOK_Orkz_Grot": 2187.5,
      "EMOK_Orkz_Boyz": 2625.0,
      "EMOK_Orkz_Mek": 2625.0,
      "EMOK_Orkz_Painboy": 2625.0,
      "EMOK_Orkz_Runtherd": 2625.0,
      "EMOK_Orkz_Weirdboy": 2625.0,
      "EMOK_Orkz_Kommando": 2625.0,
      "EMOK_Orkz_Warboss": 2625.0,
      "EMGC_BroodBrothers": 2187.5,
      "EMGC_AcolyteHybrids": 2187.5,
      "EMGC_AcolyteIconward": 5687.5,
      "EMGC_Aberrant": 2625.0,
      "EMGC_AberrantHypermorph": 2625.0,
      "EMGC_NeophyteHybrids": 2187.5,
      "EMGC_Magus": 8750.0,
      "EMGC_PurestrainGenestealer": 9625.0,
      "EMGC_Patriarch": 9187.5,
      "EMAE_Asuryani": 1750.0,
      "EMAE_Exodites": 1750.0,
      "EMTS_Tzaangor": 1750.0,
      "EMTS_TzaangorEnlightened": 1750.0,
      "EMTS_TzaangorShaman": 2625.0
    },
    "EnabledXenotypes": {
      "Baseliner": true,
      "Dirtmole": true,
      "Genie": true,
      "Hussar": true,
      "Sanguophage": true,
      "Neanderthal": true,
      "Pigskin": true,
      "Impid": true,
      "Waster": true,
      "Yttakin": true,
      "Highmate": true,
      "Starjack": true,
      "EMCM_HereticAstartes": true,
      "EMCM_HereticAstartes_Khorne": true,
      "EMCM_HereticAstartes_WorldEaters": true,
      "EMCM_HereticAstartes_Nurgle": true,
      "EMCM_HereticAstartes_DeathGuard": true,
      "EMCM_HereticAstartes_Tzeentch": true,
      "EMCM_HereticAstartes_ThousandSons": true,
      "EMCM_HereticAstartes_Slaanesh": true,
      "EMCM_HereticAstartes_EmperorsChildren": true,
      "EMCM_HereticAstartes_Undivided": true,
      "EMCM_HereticAstartes_FallenAngels": true,
      "EMCM_HereticAstartes_NightLords": true,
      "EMSM_Astartes": true,
      "EMSM_Astartes_Salamanders": true,
      "EMSM_Astartes_ImperialFists": true,
      "EMSM_Astartes_IronHands": true,
      "EMSM_Astartes_BlackTemplars": true,
      "EMSM_Astartes_CrimsonFists": true,
      "EMSM_Astartes_RavenGuard": true,
      "EMSM_Astartes_SpaceWolves": true,
      "EMSM_Astartes_LongFang": true,
      "EMSM_Astartes_Wulfen": true,
      "EMSM_Astartes_WhiteScars": true,
      "EMCH_Poxwalker": true,
      "EMNC_Necrons": true,
      "EMOK_Orkz_Grot": true,
      "EMOK_Orkz_Boyz": true,
      "EMOK_Orkz_Mek": true,
      "EMOK_Orkz_Painboy": true,
      "EMOK_Orkz_Runtherd": true,
      "EMOK_Orkz_Weirdboy": true,
      "EMOK_Orkz_Kommando": true,
      "EMOK_Orkz_Warboss": true,
      "EMGC_BroodBrothers": true,
      "EMGC_AcolyteHybrids": true,
      "EMGC_AcolyteIconward": true,
      "EMGC_Aberrant": true,
      "EMGC_AberrantHypermorph": true,
      "EMGC_NeophyteHybrids": true,
      "EMGC_Magus": true,
      "EMGC_PurestrainGenestealer": true,
      "EMGC_Patriarch": true,
      "EMAE_Asuryani": true,
      "EMAE_Exodites": true,
      "EMTS_Tzaangor": true,
      "EMTS_TzaangorEnlightened": true,
      "EMTS_TzaangorShaman": true
    }
  },
  "EMOK_GrotVanillaRace": {
    "DisplayName": "grot",
    "Enabled": true,
    "ModActive": false,
    "BasePrice": 300,
    "MinAge": 16,
    "MaxAge": 65,
    "AllowCustomXenotypes": true,
    "DefaultXenotype": "Baseliner",
    "PreferredPawnKindDefName": null,
    "AllowedGenders": {
      "AllowMale": true,
      "AllowFemale": true,
      "AllowOther": true
    },
    "XenotypePrices": {
      "Baseliner": 300.0,
      "Dirtmole": 300.0,
      "Genie": 300.0,
      "Hussar": 375.0,
      "Sanguophage": 975.0,
      "Neanderthal": 300.0,
      "Pigskin": 300.0,
      "Impid": 450.0,
      "Waster": 375.0,
      "Yttakin": 300.0,
      "Highmate": 300.0,
      "Starjack": 300.0,
      "EMCM_HereticAstartes": 300.0,
      "EMCM_HereticAstartes_Khorne": 300.0,
      "EMCM_HereticAstartes_WorldEaters": 300.0,
      "EMCM_HereticAstartes_Nurgle": 300.0,
      "EMCM_HereticAstartes_DeathGuard": 300.0,
      "EMCM_HereticAstartes_Tzeentch": 300.0,
      "EMCM_HereticAstartes_ThousandSons": 300.0,
      "EMCM_HereticAstartes_Slaanesh": 300.0,
      "EMCM_HereticAstartes_EmperorsChildren": 300.0,
      "EMCM_HereticAstartes_Undivided": 300.0,
      "EMCM_HereticAstartes_FallenAngels": 300.0,
      "EMCM_HereticAstartes_NightLords": 300.0,
      "EMSM_Astartes": 300.0,
      "EMSM_Astartes_Salamanders": 300.0,
      "EMSM_Astartes_ImperialFists": 300.0,
      "EMSM_Astartes_IronHands": 300.0,
      "EMSM_Astartes_BlackTemplars": 300.0,
      "EMSM_Astartes_CrimsonFists": 300.0,
      "EMSM_Astartes_RavenGuard": 300.0,
      "EMSM_Astartes_SpaceWolves": 300.0,
      "EMSM_Astartes_LongFang": 300.0,
      "EMSM_Astartes_Wulfen": 300.0,
      "EMSM_Astartes_WhiteScars": 300.0,
      "EMCH_Poxwalker": 300.0,
      "EMNC_Necrons": 300.0,
      "EMOK_Orkz_Grot": 375.0,
      "EMOK_Orkz_Boyz": 450.0,
      "EMOK_Orkz_Mek": 450.0,
      "EMOK_Orkz_Painboy": 450.0,
      "EMOK_Orkz_Runtherd": 450.0,
      "EMOK_Orkz_Weirdboy": 450.0,
      "EMOK_Orkz_Kommando": 450.0,
      "EMOK_Orkz_Warboss": 450.0,
      "EMGC_BroodBrothers": 375.0,
      "EMGC_AcolyteHybrids": 375.0,
      "EMGC_AcolyteIconward": 975.0,
      "EMGC_Aberrant": 450.0,
      "EMGC_AberrantHypermorph": 450.0,
      "EMGC_NeophyteHybrids": 375.0,
      "EMGC_Magus": 1500.0,
      "EMGC_PurestrainGenestealer": 1650.0,
      "EMGC_Patriarch": 1575.0,
      "EMAE_Asuryani": 300.0,
      "EMAE_Exodites": 300.0,
      "EMTS_Tzaangor": 300.0,
      "EMTS_TzaangorEnlightened": 300.0,
      "EMTS_TzaangorShaman": 450.0
    },
    "EnabledXenotypes": {
      "Baseliner": true,
      "Dirtmole": true,
      "Genie": true,
      "Hussar": true,
      "Sanguophage": true,
      "Neanderthal": true,
      "Pigskin": true,
      "Impid": true,
      "Waster": true,
      "Yttakin": true,
      "Highmate": true,
      "Starjack": true,
      "EMCM_HereticAstartes": true,
      "EMCM_HereticAstartes_Khorne": true,
      "EMCM_HereticAstartes_WorldEaters": true,
      "EMCM_HereticAstartes_Nurgle": true,
      "EMCM_HereticAstartes_DeathGuard": true,
      "EMCM_HereticAstartes_Tzeentch": true,
      "EMCM_HereticAstartes_ThousandSons": true,
      "EMCM_HereticAstartes_Slaanesh": true,
      "EMCM_HereticAstartes_EmperorsChildren": true,
      "EMCM_HereticAstartes_Undivided": true,
      "EMCM_HereticAstartes_FallenAngels": true,
      "EMCM_HereticAstartes_NightLords": true,
      "EMSM_Astartes": true,
      "EMSM_Astartes_Salamanders": true,
      "EMSM_Astartes_ImperialFists": true,
      "EMSM_Astartes_IronHands": true,
      "EMSM_Astartes_BlackTemplars": true,
      "EMSM_Astartes_CrimsonFists": true,
      "EMSM_Astartes_RavenGuard": true,
      "EMSM_Astartes_SpaceWolves": true,
      "EMSM_Astartes_LongFang": true,
      "EMSM_Astartes_Wulfen": true,
      "EMSM_Astartes_WhiteScars": true,
      "EMCH_Poxwalker": true,
      "EMNC_Necrons": true,
      "EMOK_Orkz_Grot": true,
      "EMOK_Orkz_Boyz": true,
      "EMOK_Orkz_Mek": true,
      "EMOK_Orkz_Painboy": true,
      "EMOK_Orkz_Runtherd": true,
      "EMOK_Orkz_Weirdboy": true,
      "EMOK_Orkz_Kommando": true,
      "EMOK_Orkz_Warboss": true,
      "EMGC_BroodBrothers": true,
      "EMGC_AcolyteHybrids": true,
      "EMGC_AcolyteIconward": true,
      "EMGC_Aberrant": true,
      "EMGC_AberrantHypermorph": true,
      "EMGC_NeophyteHybrids": true,
      "EMGC_Magus": true,
      "EMGC_PurestrainGenestealer": true,
      "EMGC_Patriarch": true,
      "EMAE_Asuryani": true,
      "EMAE_Exodites": true,
      "EMTS_Tzaangor": true,
      "EMTS_TzaangorEnlightened": true,
      "EMTS_TzaangorShaman": true
    }
  },
  "EMOK_OrkBoyzVanillaRace": {
    "DisplayName": "ork boyz",
    "Enabled": true,
    "ModActive": false,
    "BasePrice": 1500,
    "MinAge": 16,
    "MaxAge": 65,
    "AllowCustomXenotypes": true,
    "DefaultXenotype": "Baseliner",
    "PreferredPawnKindDefName": null,
    "AllowedGenders": {
      "AllowMale": true,
      "AllowFemale": true,
      "AllowOther": true
    },
    "XenotypePrices": {
      "Baseliner": 1500.0,
      "Dirtmole": 1500.0,
      "Genie": 1500.0,
      "Hussar": 1875.0,
      "Sanguophage": 4875.0,
      "Neanderthal": 1500.0,
      "Pigskin": 1500.0,
      "Impid": 2250.0,
      "Waster": 1875.0,
      "Yttakin": 1500.0,
      "Highmate": 1500.0,
      "Starjack": 1500.0,
      "EMCM_HereticAstartes": 1500.0,
      "EMCM_HereticAstartes_Khorne": 1500.0,
      "EMCM_HereticAstartes_WorldEaters": 1500.0,
      "EMCM_HereticAstartes_Nurgle": 1500.0,
      "EMCM_HereticAstartes_DeathGuard": 1500.0,
      "EMCM_HereticAstartes_Tzeentch": 1500.0,
      "EMCM_HereticAstartes_ThousandSons": 1500.0,
      "EMCM_HereticAstartes_Slaanesh": 1500.0,
      "EMCM_HereticAstartes_EmperorsChildren": 1500.0,
      "EMCM_HereticAstartes_Undivided": 1500.0,
      "EMCM_HereticAstartes_FallenAngels": 1500.0,
      "EMCM_HereticAstartes_NightLords": 1500.0,
      "EMSM_Astartes": 1500.0,
      "EMSM_Astartes_Salamanders": 1500.0,
      "EMSM_Astartes_ImperialFists": 1500.0,
      "EMSM_Astartes_IronHands": 1500.0,
      "EMSM_Astartes_BlackTemplars": 1500.0,
      "EMSM_Astartes_CrimsonFists": 1500.0,
      "EMSM_Astartes_RavenGuard": 1500.0,
      "EMSM_Astartes_SpaceWolves": 1500.0,
      "EMSM_Astartes_LongFang": 1500.0,
      "EMSM_Astartes_Wulfen": 1500.0,
      "EMSM_Astartes_WhiteScars": 1500.0,
      "EMCH_Poxwalker": 1500.0,
      "EMNC_Necrons": 1500.0,
      "EMOK_Orkz_Grot": 1875.0,
      "EMOK_Orkz_Boyz": 2250.0,
      "EMOK_Orkz_Mek": 2250.0,
      "EMOK_Orkz_Painboy": 2250.0,
      "EMOK_Orkz_Runtherd": 2250.0,
      "EMOK_Orkz_Weirdboy": 2250.0,
      "EMOK_Orkz_Kommando": 2250.0,
      "EMOK_Orkz_Warboss": 2250.0,
      "EMGC_BroodBrothers": 1875.0,
      "EMGC_AcolyteHybrids": 1875.0,
      "EMGC_AcolyteIconward": 4875.0,
      "EMGC_Aberrant": 2250.0,
      "EMGC_AberrantHypermorph": 2250.0,
      "EMGC_NeophyteHybrids": 1875.0,
      "EMGC_Magus": 7500.0,
      "EMGC_PurestrainGenestealer": 8250.0,
      "EMGC_Patriarch": 7875.0,
      "EMAE_Asuryani": 1500.0,
      "EMAE_Exodites": 1500.0,
      "EMTS_Tzaangor": 1500.0,
      "EMTS_TzaangorEnlightened": 1500.0,
      "EMTS_TzaangorShaman": 2250.0
    },
    "EnabledXenotypes": {
      "Baseliner": true,
      "Dirtmole": true,
      "Genie": true,
      "Hussar": true,
      "Sanguophage": true,
      "Neanderthal": true,
      "Pigskin": true,
      "Impid": true,
      "Waster": true,
      "Yttakin": true,
      "Highmate": true,
      "Starjack": true,
      "EMCM_HereticAstartes": true,
      "EMCM_HereticAstartes_Khorne": true,
      "EMCM_HereticAstartes_WorldEaters": true,
      "EMCM_HereticAstartes_Nurgle": true,
      "EMCM_HereticAstartes_DeathGuard": true,
      "EMCM_HereticAstartes_Tzeentch": true,
      "EMCM_HereticAstartes_ThousandSons": true,
      "EMCM_HereticAstartes_Slaanesh": true,
      "EMCM_HereticAstartes_EmperorsChildren": true,
      "EMCM_HereticAstartes_Undivided": true,
      "EMCM_HereticAstartes_FallenAngels": true,
      "EMCM_HereticAstartes_NightLords": true,
      "EMSM_Astartes": true,
      "EMSM_Astartes_Salamanders": true,
      "EMSM_Astartes_ImperialFists": true,
      "EMSM_Astartes_IronHands": true,
      "EMSM_Astartes_BlackTemplars": true,
      "EMSM_Astartes_CrimsonFists": true,
      "EMSM_Astartes_RavenGuard": true,
      "EMSM_Astartes_SpaceWolves": true,
      "EMSM_Astartes_LongFang": true,
      "EMSM_Astartes_Wulfen": true,
      "EMSM_Astartes_WhiteScars": true,
      "EMCH_Poxwalker": true,
      "EMNC_Necrons": true,
      "EMOK_Orkz_Grot": true,
      "EMOK_Orkz_Boyz": true,
      "EMOK_Orkz_Mek": true,
      "EMOK_Orkz_Painboy": true,
      "EMOK_Orkz_Runtherd": true,
      "EMOK_Orkz_Weirdboy": true,
      "EMOK_Orkz_Kommando": true,
      "EMOK_Orkz_Warboss": true,
      "EMGC_BroodBrothers": true,
      "EMGC_AcolyteHybrids": true,
      "EMGC_AcolyteIconward": true,
      "EMGC_Aberrant": true,
      "EMGC_AberrantHypermorph": true,
      "EMGC_NeophyteHybrids": true,
      "EMGC_Magus": true,
      "EMGC_PurestrainGenestealer": true,
      "EMGC_Patriarch": true,
      "EMAE_Asuryani": true,
      "EMAE_Exodites": true,
      "EMTS_Tzaangor": true,
      "EMTS_TzaangorEnlightened": true,
      "EMTS_TzaangorShaman": true
    }
  },
  "EMOK_OrkMekVanillaRace": {
    "DisplayName": "ork mek",
    "Enabled": true,
    "ModActive": false,
    "BasePrice": 1500,
    "MinAge": 16,
    "MaxAge": 65,
    "AllowCustomXenotypes": true,
    "DefaultXenotype": "Baseliner",
    "PreferredPawnKindDefName": null,
    "AllowedGenders": {
      "AllowMale": true,
      "AllowFemale": true,
      "AllowOther": true
    },
    "XenotypePrices": {
      "Baseliner": 1500.0,
      "Dirtmole": 1500.0,
      "Genie": 1500.0,
      "Hussar": 1875.0,
      "Sanguophage": 4875.0,
      "Neanderthal": 1500.0,
      "Pigskin": 1500.0,
      "Impid": 2250.0,
      "Waster": 1875.0,
      "Yttakin": 1500.0,
      "Highmate": 1500.0,
      "Starjack": 1500.0,
      "EMCM_HereticAstartes": 1500.0,
      "EMCM_HereticAstartes_Khorne": 1500.0,
      "EMCM_HereticAstartes_WorldEaters": 1500.0,
      "EMCM_HereticAstartes_Nurgle": 1500.0,
      "EMCM_HereticAstartes_DeathGuard": 1500.0,
      "EMCM_HereticAstartes_Tzeentch": 1500.0,
      "EMCM_HereticAstartes_ThousandSons": 1500.0,
      "EMCM_HereticAstartes_Slaanesh": 1500.0,
      "EMCM_HereticAstartes_EmperorsChildren": 1500.0,
      "EMCM_HereticAstartes_Undivided": 1500.0,
      "EMCM_HereticAstartes_FallenAngels": 1500.0,
      "EMCM_HereticAstartes_NightLords": 1500.0,
      "EMSM_Astartes": 1500.0,
      "EMSM_Astartes_Salamanders": 1500.0,
      "EMSM_Astartes_ImperialFists": 1500.0,
      "EMSM_Astartes_IronHands": 1500.0,
      "EMSM_Astartes_BlackTemplars": 1500.0,
      "EMSM_Astartes_CrimsonFists": 1500.0,
      "EMSM_Astartes_RavenGuard": 1500.0,
      "EMSM_Astartes_SpaceWolves": 1500.0,
      "EMSM_Astartes_LongFang": 1500.0,
      "EMSM_Astartes_Wulfen": 1500.0,
      "EMSM_Astartes_WhiteScars": 1500.0,
      "EMCH_Poxwalker": 1500.0,
      "EMNC_Necrons": 1500.0,
      "EMOK_Orkz_Grot": 1875.0,
      "EMOK_Orkz_Boyz": 2250.0,
      "EMOK_Orkz_Mek": 2250.0,
      "EMOK_Orkz_Painboy": 2250.0,
      "EMOK_Orkz_Runtherd": 2250.0,
      "EMOK_Orkz_Weirdboy": 2250.0,
      "EMOK_Orkz_Kommando": 2250.0,
      "EMOK_Orkz_Warboss": 2250.0,
      "EMGC_BroodBrothers": 1875.0,
      "EMGC_AcolyteHybrids": 1875.0,
      "EMGC_AcolyteIconward": 4875.0,
      "EMGC_Aberrant": 2250.0,
      "EMGC_AberrantHypermorph": 2250.0,
      "EMGC_NeophyteHybrids": 1875.0,
      "EMGC_Magus": 7500.0,
      "EMGC_PurestrainGenestealer": 8250.0,
      "EMGC_Patriarch": 7875.0,
      "EMAE_Asuryani": 1500.0,
      "EMAE_Exodites": 1500.0,
      "EMTS_Tzaangor": 1500.0,
      "EMTS_TzaangorEnlightened": 1500.0,
      "EMTS_TzaangorShaman": 2250.0
    },
    "EnabledXenotypes": {
      "Baseliner": true,
      "Dirtmole": true,
      "Genie": true,
      "Hussar": true,
      "Sanguophage": true,
      "Neanderthal": true,
      "Pigskin": true,
      "Impid": true,
      "Waster": true,
      "Yttakin": true,
      "Highmate": true,
      "Starjack": true,
      "EMCM_HereticAstartes": true,
      "EMCM_HereticAstartes_Khorne": true,
      "EMCM_HereticAstartes_WorldEaters": true,
      "EMCM_HereticAstartes_Nurgle": true,
      "EMCM_HereticAstartes_DeathGuard": true,
      "EMCM_HereticAstartes_Tzeentch": true,
      "EMCM_HereticAstartes_ThousandSons": true,
      "EMCM_HereticAstartes_Slaanesh": true,
      "EMCM_HereticAstartes_EmperorsChildren": true,
      "EMCM_HereticAstartes_Undivided": true,
      "EMCM_HereticAstartes_FallenAngels": true,
      "EMCM_HereticAstartes_NightLords": true,
      "EMSM_Astartes": true,
      "EMSM_Astartes_Salamanders": true,
      "EMSM_Astartes_ImperialFists": true,
      "EMSM_Astartes_IronHands": true,
      "EMSM_Astartes_BlackTemplars": true,
      "EMSM_Astartes_CrimsonFists": true,
      "EMSM_Astartes_RavenGuard": true,
      "EMSM_Astartes_SpaceWolves": true,
      "EMSM_Astartes_LongFang": true,
      "EMSM_Astartes_Wulfen": true,
      "EMSM_Astartes_WhiteScars": true,
      "EMCH_Poxwalker": true,
      "EMNC_Necrons": true,
      "EMOK_Orkz_Grot": true,
      "EMOK_Orkz_Boyz": true,
      "EMOK_Orkz_Mek": true,
      "EMOK_Orkz_Painboy": true,
      "EMOK_Orkz_Runtherd": true,
      "EMOK_Orkz_Weirdboy": true,
      "EMOK_Orkz_Kommando": true,
      "EMOK_Orkz_Warboss": true,
      "EMGC_BroodBrothers": true,
      "EMGC_AcolyteHybrids": true,
      "EMGC_AcolyteIconward": true,
      "EMGC_Aberrant": true,
      "EMGC_AberrantHypermorph": true,
      "EMGC_NeophyteHybrids": true,
      "EMGC_Magus": true,
      "EMGC_PurestrainGenestealer": true,
      "EMGC_Patriarch": true,
      "EMAE_Asuryani": true,
      "EMAE_Exodites": true,
      "EMTS_Tzaangor": true,
      "EMTS_TzaangorEnlightened": true,
      "EMTS_TzaangorShaman": true
    }
  },
  "EMOK_OrkPainboyVanillaRace": {
    "DisplayName": "ork painboy",
    "Enabled": true,
    "ModActive": false,
    "BasePrice": 1500,
    "MinAge": 16,
    "MaxAge": 65,
    "AllowCustomXenotypes": true,
    "DefaultXenotype": "Baseliner",
    "PreferredPawnKindDefName": null,
    "AllowedGenders": {
      "AllowMale": true,
      "AllowFemale": true,
      "AllowOther": true
    },
    "XenotypePrices": {
      "Baseliner": 1500.0,
      "Dirtmole": 1500.0,
      "Genie": 1500.0,
      "Hussar": 1875.0,
      "Sanguophage": 4875.0,
      "Neanderthal": 1500.0,
      "Pigskin": 1500.0,
      "Impid": 2250.0,
      "Waster": 1875.0,
      "Yttakin": 1500.0,
      "Highmate": 1500.0,
      "Starjack": 1500.0,
      "EMCM_HereticAstartes": 1500.0,
      "EMCM_HereticAstartes_Khorne": 1500.0,
      "EMCM_HereticAstartes_WorldEaters": 1500.0,
      "EMCM_HereticAstartes_Nurgle": 1500.0,
      "EMCM_HereticAstartes_DeathGuard": 1500.0,
      "EMCM_HereticAstartes_Tzeentch": 1500.0,
      "EMCM_HereticAstartes_ThousandSons": 1500.0,
      "EMCM_HereticAstartes_Slaanesh": 1500.0,
      "EMCM_HereticAstartes_EmperorsChildren": 1500.0,
      "EMCM_HereticAstartes_Undivided": 1500.0,
      "EMCM_HereticAstartes_FallenAngels": 1500.0,
      "EMCM_HereticAstartes_NightLords": 1500.0,
      "EMSM_Astartes": 1500.0,
      "EMSM_Astartes_Salamanders": 1500.0,
      "EMSM_Astartes_ImperialFists": 1500.0,
      "EMSM_Astartes_IronHands": 1500.0,
      "EMSM_Astartes_BlackTemplars": 1500.0,
      "EMSM_Astartes_CrimsonFists": 1500.0,
      "EMSM_Astartes_RavenGuard": 1500.0,
      "EMSM_Astartes_SpaceWolves": 1500.0,
      "EMSM_Astartes_LongFang": 1500.0,
      "EMSM_Astartes_Wulfen": 1500.0,
      "EMSM_Astartes_WhiteScars": 1500.0,
      "EMCH_Poxwalker": 1500.0,
      "EMNC_Necrons": 1500.0,
      "EMOK_Orkz_Grot": 1875.0,
      "EMOK_Orkz_Boyz": 2250.0,
      "EMOK_Orkz_Mek": 2250.0,
      "EMOK_Orkz_Painboy": 2250.0,
      "EMOK_Orkz_Runtherd": 2250.0,
      "EMOK_Orkz_Weirdboy": 2250.0,
      "EMOK_Orkz_Kommando": 2250.0,
      "EMOK_Orkz_Warboss": 2250.0,
      "EMGC_BroodBrothers": 1875.0,
      "EMGC_AcolyteHybrids": 1875.0,
      "EMGC_AcolyteIconward": 4875.0,
      "EMGC_Aberrant": 2250.0,
      "EMGC_AberrantHypermorph": 2250.0,
      "EMGC_NeophyteHybrids": 1875.0,
      "EMGC_Magus": 7500.0,
      "EMGC_PurestrainGenestealer": 8250.0,
      "EMGC_Patriarch": 7875.0,
      "EMAE_Asuryani": 1500.0,
      "EMAE_Exodites": 1500.0,
      "EMTS_Tzaangor": 1500.0,
      "EMTS_TzaangorEnlightened": 1500.0,
      "EMTS_TzaangorShaman": 2250.0
    },
    "EnabledXenotypes": {
      "Baseliner": true,
      "Dirtmole": true,
      "Genie": true,
      "Hussar": true,
      "Sanguophage": true,
      "Neanderthal": true,
      "Pigskin": true,
      "Impid": true,
      "Waster": true,
      "Yttakin": true,
      "Highmate": true,
      "Starjack": true,
      "EMCM_HereticAstartes": true,
      "EMCM_HereticAstartes_Khorne": true,
      "EMCM_HereticAstartes_WorldEaters": true,
      "EMCM_HereticAstartes_Nurgle": true,
      "EMCM_HereticAstartes_DeathGuard": true,
      "EMCM_HereticAstartes_Tzeentch": true,
      "EMCM_HereticAstartes_ThousandSons": true,
      "EMCM_HereticAstartes_Slaanesh": true,
      "EMCM_HereticAstartes_EmperorsChildren": true,
      "EMCM_HereticAstartes_Undivided": true,
      "EMCM_HereticAstartes_FallenAngels": true,
      "EMCM_HereticAstartes_NightLords": true,
      "EMSM_Astartes": true,
      "EMSM_Astartes_Salamanders": true,
      "EMSM_Astartes_ImperialFists": true,
      "EMSM_Astartes_IronHands": true,
      "EMSM_Astartes_BlackTemplars": true,
      "EMSM_Astartes_CrimsonFists": true,
      "EMSM_Astartes_RavenGuard": true,
      "EMSM_Astartes_SpaceWolves": true,
      "EMSM_Astartes_LongFang": true,
      "EMSM_Astartes_Wulfen": true,
      "EMSM_Astartes_WhiteScars": true,
      "EMCH_Poxwalker": true,
      "EMNC_Necrons": true,
      "EMOK_Orkz_Grot": true,
      "EMOK_Orkz_Boyz": true,
      "EMOK_Orkz_Mek": true,
      "EMOK_Orkz_Painboy": true,
      "EMOK_Orkz_Runtherd": true,
      "EMOK_Orkz_Weirdboy": true,
      "EMOK_Orkz_Kommando": true,
      "EMOK_Orkz_Warboss": true,
      "EMGC_BroodBrothers": true,
      "EMGC_AcolyteHybrids": true,
      "EMGC_AcolyteIconward": true,
      "EMGC_Aberrant": true,
      "EMGC_AberrantHypermorph": true,
      "EMGC_NeophyteHybrids": true,
      "EMGC_Magus": true,
      "EMGC_PurestrainGenestealer": true,
      "EMGC_Patriarch": true,
      "EMAE_Asuryani": true,
      "EMAE_Exodites": true,
      "EMTS_Tzaangor": true,
      "EMTS_TzaangorEnlightened": true,
      "EMTS_TzaangorShaman": true
    }
  },
  "EMOK_OrkWeirdboyVanillaRace": {
    "DisplayName": "ork weirdboy",
    "Enabled": true,
    "ModActive": false,
    "BasePrice": 1500,
    "MinAge": 16,
    "MaxAge": 65,
    "AllowCustomXenotypes": true,
    "DefaultXenotype": "Baseliner",
    "PreferredPawnKindDefName": null,
    "AllowedGenders": {
      "AllowMale": true,
      "AllowFemale": true,
      "AllowOther": true
    },
    "XenotypePrices": {
      "Baseliner": 1500.0,
      "Dirtmole": 1500.0,
      "Genie": 1500.0,
      "Hussar": 1875.0,
      "Sanguophage": 4875.0,
      "Neanderthal": 1500.0,
      "Pigskin": 1500.0,
      "Impid": 2250.0,
      "Waster": 1875.0,
      "Yttakin": 1500.0,
      "Highmate": 1500.0,
      "Starjack": 1500.0,
      "EMCM_HereticAstartes": 1500.0,
      "EMCM_HereticAstartes_Khorne": 1500.0,
      "EMCM_HereticAstartes_WorldEaters": 1500.0,
      "EMCM_HereticAstartes_Nurgle": 1500.0,
      "EMCM_HereticAstartes_DeathGuard": 1500.0,
      "EMCM_HereticAstartes_Tzeentch": 1500.0,
      "EMCM_HereticAstartes_ThousandSons": 1500.0,
      "EMCM_HereticAstartes_Slaanesh": 1500.0,
      "EMCM_HereticAstartes_EmperorsChildren": 1500.0,
      "EMCM_HereticAstartes_Undivided": 1500.0,
      "EMCM_HereticAstartes_FallenAngels": 1500.0,
      "EMCM_HereticAstartes_NightLords": 1500.0,
      "EMSM_Astartes": 1500.0,
      "EMSM_Astartes_Salamanders": 1500.0,
      "EMSM_Astartes_ImperialFists": 1500.0,
      "EMSM_Astartes_IronHands": 1500.0,
      "EMSM_Astartes_BlackTemplars": 1500.0,
      "EMSM_Astartes_CrimsonFists": 1500.0,
      "EMSM_Astartes_RavenGuard": 1500.0,
      "EMSM_Astartes_SpaceWolves": 1500.0,
      "EMSM_Astartes_LongFang": 1500.0,
      "EMSM_Astartes_Wulfen": 1500.0,
      "EMSM_Astartes_WhiteScars": 1500.0,
      "EMCH_Poxwalker": 1500.0,
      "EMNC_Necrons": 1500.0,
      "EMOK_Orkz_Grot": 1875.0,
      "EMOK_Orkz_Boyz": 2250.0,
      "EMOK_Orkz_Mek": 2250.0,
      "EMOK_Orkz_Painboy": 2250.0,
      "EMOK_Orkz_Runtherd": 2250.0,
      "EMOK_Orkz_Weirdboy": 2250.0,
      "EMOK_Orkz_Kommando": 2250.0,
      "EMOK_Orkz_Warboss": 2250.0,
      "EMGC_BroodBrothers": 1875.0,
      "EMGC_AcolyteHybrids": 1875.0,
      "EMGC_AcolyteIconward": 4875.0,
      "EMGC_Aberrant": 2250.0,
      "EMGC_AberrantHypermorph": 2250.0,
      "EMGC_NeophyteHybrids": 1875.0,
      "EMGC_Magus": 7500.0,
      "EMGC_PurestrainGenestealer": 8250.0,
      "EMGC_Patriarch": 7875.0,
      "EMAE_Asuryani": 1500.0,
      "EMAE_Exodites": 1500.0,
      "EMTS_Tzaangor": 1500.0,
      "EMTS_TzaangorEnlightened": 1500.0,
      "EMTS_TzaangorShaman": 2250.0
    },
    "EnabledXenotypes": {
      "Baseliner": true,
      "Dirtmole": true,
      "Genie": true,
      "Hussar": true,
      "Sanguophage": true,
      "Neanderthal": true,
      "Pigskin": true,
      "Impid": true,
      "Waster": true,
      "Yttakin": true,
      "Highmate": true,
      "Starjack": true,
      "EMCM_HereticAstartes": true,
      "EMCM_HereticAstartes_Khorne": true,
      "EMCM_HereticAstartes_WorldEaters": true,
      "EMCM_HereticAstartes_Nurgle": true,
      "EMCM_HereticAstartes_DeathGuard": true,
      "EMCM_HereticAstartes_Tzeentch": true,
      "EMCM_HereticAstartes_ThousandSons": true,
      "EMCM_HereticAstartes_Slaanesh": true,
      "EMCM_HereticAstartes_EmperorsChildren": true,
      "EMCM_HereticAstartes_Undivided": true,
      "EMCM_HereticAstartes_FallenAngels": true,
      "EMCM_HereticAstartes_NightLords": true,
      "EMSM_Astartes": true,
      "EMSM_Astartes_Salamanders": true,
      "EMSM_Astartes_ImperialFists": true,
      "EMSM_Astartes_IronHands": true,
      "EMSM_Astartes_BlackTemplars": true,
      "EMSM_Astartes_CrimsonFists": true,
      "EMSM_Astartes_RavenGuard": true,
      "EMSM_Astartes_SpaceWolves": true,
      "EMSM_Astartes_LongFang": true,
      "EMSM_Astartes_Wulfen": true,
      "EMSM_Astartes_WhiteScars": true,
      "EMCH_Poxwalker": true,
      "EMNC_Necrons": true,
      "EMOK_Orkz_Grot": true,
      "EMOK_Orkz_Boyz": true,
      "EMOK_Orkz_Mek": true,
      "EMOK_Orkz_Painboy": true,
      "EMOK_Orkz_Runtherd": true,
      "EMOK_Orkz_Weirdboy": true,
      "EMOK_Orkz_Kommando": true,
      "EMOK_Orkz_Warboss": true,
      "EMGC_BroodBrothers": true,
      "EMGC_AcolyteHybrids": true,
      "EMGC_AcolyteIconward": true,
      "EMGC_Aberrant": true,
      "EMGC_AberrantHypermorph": true,
      "EMGC_NeophyteHybrids": true,
      "EMGC_Magus": true,
      "EMGC_PurestrainGenestealer": true,
      "EMGC_Patriarch": true,
      "EMAE_Asuryani": true,
      "EMAE_Exodites": true,
      "EMTS_Tzaangor": true,
      "EMTS_TzaangorEnlightened": true,
      "EMTS_TzaangorShaman": true
    }
  },
  "EMOK_OrkRuntherdVanillaRace": {
    "DisplayName": "ork runtherd",
    "Enabled": true,
    "ModActive": false,
    "BasePrice": 1500,
    "MinAge": 16,
    "MaxAge": 65,
    "AllowCustomXenotypes": true,
    "DefaultXenotype": "Baseliner",
    "PreferredPawnKindDefName": null,
    "AllowedGenders": {
      "AllowMale": true,
      "AllowFemale": true,
      "AllowOther": true
    },
    "XenotypePrices": {
      "Baseliner": 1500.0,
      "Dirtmole": 1500.0,
      "Genie": 1500.0,
      "Hussar": 1875.0,
      "Sanguophage": 4875.0,
      "Neanderthal": 1500.0,
      "Pigskin": 1500.0,
      "Impid": 2250.0,
      "Waster": 1875.0,
      "Yttakin": 1500.0,
      "Highmate": 1500.0,
      "Starjack": 1500.0,
      "EMCM_HereticAstartes": 1500.0,
      "EMCM_HereticAstartes_Khorne": 1500.0,
      "EMCM_HereticAstartes_WorldEaters": 1500.0,
      "EMCM_HereticAstartes_Nurgle": 1500.0,
      "EMCM_HereticAstartes_DeathGuard": 1500.0,
      "EMCM_HereticAstartes_Tzeentch": 1500.0,
      "EMCM_HereticAstartes_ThousandSons": 1500.0,
      "EMCM_HereticAstartes_Slaanesh": 1500.0,
      "EMCM_HereticAstartes_EmperorsChildren": 1500.0,
      "EMCM_HereticAstartes_Undivided": 1500.0,
      "EMCM_HereticAstartes_FallenAngels": 1500.0,
      "EMCM_HereticAstartes_NightLords": 1500.0,
      "EMSM_Astartes": 1500.0,
      "EMSM_Astartes_Salamanders": 1500.0,
      "EMSM_Astartes_ImperialFists": 1500.0,
      "EMSM_Astartes_IronHands": 1500.0,
      "EMSM_Astartes_BlackTemplars": 1500.0,
      "EMSM_Astartes_CrimsonFists": 1500.0,
      "EMSM_Astartes_RavenGuard": 1500.0,
      "EMSM_Astartes_SpaceWolves": 1500.0,
      "EMSM_Astartes_LongFang": 1500.0,
      "EMSM_Astartes_Wulfen": 1500.0,
      "EMSM_Astartes_WhiteScars": 1500.0,
      "EMCH_Poxwalker": 1500.0,
      "EMNC_Necrons": 1500.0,
      "EMOK_Orkz_Grot": 1875.0,
      "EMOK_Orkz_Boyz": 2250.0,
      "EMOK_Orkz_Mek": 2250.0,
      "EMOK_Orkz_Painboy": 2250.0,
      "EMOK_Orkz_Runtherd": 2250.0,
      "EMOK_Orkz_Weirdboy": 2250.0,
      "EMOK_Orkz_Kommando": 2250.0,
      "EMOK_Orkz_Warboss": 2250.0,
      "EMGC_BroodBrothers": 1875.0,
      "EMGC_AcolyteHybrids": 1875.0,
      "EMGC_AcolyteIconward": 4875.0,
      "EMGC_Aberrant": 2250.0,
      "EMGC_AberrantHypermorph": 2250.0,
      "EMGC_NeophyteHybrids": 1875.0,
      "EMGC_Magus": 7500.0,
      "EMGC_PurestrainGenestealer": 8250.0,
      "EMGC_Patriarch": 7875.0,
      "EMAE_Asuryani": 1500.0,
      "EMAE_Exodites": 1500.0,
      "EMTS_Tzaangor": 1500.0,
      "EMTS_TzaangorEnlightened": 1500.0,
      "EMTS_TzaangorShaman": 2250.0
    },
    "EnabledXenotypes": {
      "Baseliner": true,
      "Dirtmole": true,
      "Genie": true,
      "Hussar": true,
      "Sanguophage": true,
      "Neanderthal": true,
      "Pigskin": true,
      "Impid": true,
      "Waster": true,
      "Yttakin": true,
      "Highmate": true,
      "Starjack": true,
      "EMCM_HereticAstartes": true,
      "EMCM_HereticAstartes_Khorne": true,
      "EMCM_HereticAstartes_WorldEaters": true,
      "EMCM_HereticAstartes_Nurgle": true,
      "EMCM_HereticAstartes_DeathGuard": true,
      "EMCM_HereticAstartes_Tzeentch": true,
      "EMCM_HereticAstartes_ThousandSons": true,
      "EMCM_HereticAstartes_Slaanesh": true,
      "EMCM_HereticAstartes_EmperorsChildren": true,
      "EMCM_HereticAstartes_Undivided": true,
      "EMCM_HereticAstartes_FallenAngels": true,
      "EMCM_HereticAstartes_NightLords": true,
      "EMSM_Astartes": true,
      "EMSM_Astartes_Salamanders": true,
      "EMSM_Astartes_ImperialFists": true,
      "EMSM_Astartes_IronHands": true,
      "EMSM_Astartes_BlackTemplars": true,
      "EMSM_Astartes_CrimsonFists": true,
      "EMSM_Astartes_RavenGuard": true,
      "EMSM_Astartes_SpaceWolves": true,
      "EMSM_Astartes_LongFang": true,
      "EMSM_Astartes_Wulfen": true,
      "EMSM_Astartes_WhiteScars": true,
      "EMCH_Poxwalker": true,
      "EMNC_Necrons": true,
      "EMOK_Orkz_Grot": true,
      "EMOK_Orkz_Boyz": true,
      "EMOK_Orkz_Mek": true,
      "EMOK_Orkz_Painboy": true,
      "EMOK_Orkz_Runtherd": true,
      "EMOK_Orkz_Weirdboy": true,
      "EMOK_Orkz_Kommando": true,
      "EMOK_Orkz_Warboss": true,
      "EMGC_BroodBrothers": true,
      "EMGC_AcolyteHybrids": true,
      "EMGC_AcolyteIconward": true,
      "EMGC_Aberrant": true,
      "EMGC_AberrantHypermorph": true,
      "EMGC_NeophyteHybrids": true,
      "EMGC_Magus": true,
      "EMGC_PurestrainGenestealer": true,
      "EMGC_Patriarch": true,
      "EMAE_Asuryani": true,
      "EMAE_Exodites": true,
      "EMTS_Tzaangor": true,
      "EMTS_TzaangorEnlightened": true,
      "EMTS_TzaangorShaman": true
    }
  },
  "EMOK_OrkWarbossVanillaRace": {
    "DisplayName": "ork warboss",
    "Enabled": true,
    "ModActive": false,
    "BasePrice": 1500,
    "MinAge": 16,
    "MaxAge": 65,
    "AllowCustomXenotypes": true,
    "DefaultXenotype": "Baseliner",
    "PreferredPawnKindDefName": null,
    "AllowedGenders": {
      "AllowMale": true,
      "AllowFemale": true,
      "AllowOther": true
    },
    "XenotypePrices": {
      "Baseliner": 1500.0,
      "Dirtmole": 1500.0,
      "Genie": 1500.0,
      "Hussar": 1875.0,
      "Sanguophage": 4875.0,
      "Neanderthal": 1500.0,
      "Pigskin": 1500.0,
      "Impid": 2250.0,
      "Waster": 1875.0,
      "Yttakin": 1500.0,
      "Highmate": 1500.0,
      "Starjack": 1500.0,
      "EMCM_HereticAstartes": 1500.0,
      "EMCM_HereticAstartes_Khorne": 1500.0,
      "EMCM_HereticAstartes_WorldEaters": 1500.0,
      "EMCM_HereticAstartes_Nurgle": 1500.0,
      "EMCM_HereticAstartes_DeathGuard": 1500.0,
      "EMCM_HereticAstartes_Tzeentch": 1500.0,
      "EMCM_HereticAstartes_ThousandSons": 1500.0,
      "EMCM_HereticAstartes_Slaanesh": 1500.0,
      "EMCM_HereticAstartes_EmperorsChildren": 1500.0,
      "EMCM_HereticAstartes_Undivided": 1500.0,
      "EMCM_HereticAstartes_FallenAngels": 1500.0,
      "EMCM_HereticAstartes_NightLords": 1500.0,
      "EMSM_Astartes": 1500.0,
      "EMSM_Astartes_Salamanders": 1500.0,
      "EMSM_Astartes_ImperialFists": 1500.0,
      "EMSM_Astartes_IronHands": 1500.0,
      "EMSM_Astartes_BlackTemplars": 1500.0,
      "EMSM_Astartes_CrimsonFists": 1500.0,
      "EMSM_Astartes_RavenGuard": 1500.0,
      "EMSM_Astartes_SpaceWolves": 1500.0,
      "EMSM_Astartes_LongFang": 1500.0,
      "EMSM_Astartes_Wulfen": 1500.0,
      "EMSM_Astartes_WhiteScars": 1500.0,
      "EMCH_Poxwalker": 1500.0,
      "EMNC_Necrons": 1500.0,
      "EMOK_Orkz_Grot": 1875.0,
      "EMOK_Orkz_Boyz": 2250.0,
      "EMOK_Orkz_Mek": 2250.0,
      "EMOK_Orkz_Painboy": 2250.0,
      "EMOK_Orkz_Runtherd": 2250.0,
      "EMOK_Orkz_Weirdboy": 2250.0,
      "EMOK_Orkz_Kommando": 2250.0,
      "EMOK_Orkz_Warboss": 2250.0,
      "EMGC_BroodBrothers": 1875.0,
      "EMGC_AcolyteHybrids": 1875.0,
      "EMGC_AcolyteIconward": 4875.0,
      "EMGC_Aberrant": 2250.0,
      "EMGC_AberrantHypermorph": 2250.0,
      "EMGC_NeophyteHybrids": 1875.0,
      "EMGC_Magus": 7500.0,
      "EMGC_PurestrainGenestealer": 8250.0,
      "EMGC_Patriarch": 7875.0,
      "EMAE_Asuryani": 1500.0,
      "EMAE_Exodites": 1500.0,
      "EMTS_Tzaangor": 1500.0,
      "EMTS_TzaangorEnlightened": 1500.0,
      "EMTS_TzaangorShaman": 2250.0
    },
    "EnabledXenotypes": {
      "Baseliner": true,
      "Dirtmole": true,
      "Genie": true,
      "Hussar": true,
      "Sanguophage": true,
      "Neanderthal": true,
      "Pigskin": true,
      "Impid": true,
      "Waster": true,
      "Yttakin": true,
      "Highmate": true,
      "Starjack": true,
      "EMCM_HereticAstartes": true,
      "EMCM_HereticAstartes_Khorne": true,
      "EMCM_HereticAstartes_WorldEaters": true,
      "EMCM_HereticAstartes_Nurgle": true,
      "EMCM_HereticAstartes_DeathGuard": true,
      "EMCM_HereticAstartes_Tzeentch": true,
      "EMCM_HereticAstartes_ThousandSons": true,
      "EMCM_HereticAstartes_Slaanesh": true,
      "EMCM_HereticAstartes_EmperorsChildren": true,
      "EMCM_HereticAstartes_Undivided": true,
      "EMCM_HereticAstartes_FallenAngels": true,
      "EMCM_HereticAstartes_NightLords": true,
      "EMSM_Astartes": true,
      "EMSM_Astartes_Salamanders": true,
      "EMSM_Astartes_ImperialFists": true,
      "EMSM_Astartes_IronHands": true,
      "EMSM_Astartes_BlackTemplars": true,
      "EMSM_Astartes_CrimsonFists": true,
      "EMSM_Astartes_RavenGuard": true,
      "EMSM_Astartes_SpaceWolves": true,
      "EMSM_Astartes_LongFang": true,
      "EMSM_Astartes_Wulfen": true,
      "EMSM_Astartes_WhiteScars": true,
      "EMCH_Poxwalker": true,
      "EMNC_Necrons": true,
      "EMOK_Orkz_Grot": true,
      "EMOK_Orkz_Boyz": true,
      "EMOK_Orkz_Mek": true,
      "EMOK_Orkz_Painboy": true,
      "EMOK_Orkz_Runtherd": true,
      "EMOK_Orkz_Weirdboy": true,
      "EMOK_Orkz_Kommando": true,
      "EMOK_Orkz_Warboss": true,
      "EMGC_BroodBrothers": true,
      "EMGC_AcolyteHybrids": true,
      "EMGC_AcolyteIconward": true,
      "EMGC_Aberrant": true,
      "EMGC_AberrantHypermorph": true,
      "EMGC_NeophyteHybrids": true,
      "EMGC_Magus": true,
      "EMGC_PurestrainGenestealer": true,
      "EMGC_Patriarch": true,
      "EMAE_Asuryani": true,
      "EMAE_Exodites": true,
      "EMTS_Tzaangor": true,
      "EMTS_TzaangorEnlightened": true,
      "EMTS_TzaangorShaman": true
    }
  },
  "EMGC_PurestrainGenestealerVanillaRace": {
    "DisplayName": "purestrain genestealer",
    "Enabled": true,
    "ModActive": false,
    "BasePrice": 2000,
    "MinAge": 16,
    "MaxAge": 65,
    "AllowCustomXenotypes": true,
    "DefaultXenotype": "Baseliner",
    "PreferredPawnKindDefName": null,
    "AllowedGenders": {
      "AllowMale": true,
      "AllowFemale": true,
      "AllowOther": true
    },
    "XenotypePrices": {
      "Baseliner": 2000.0,
      "Dirtmole": 2000.0,
      "Genie": 2000.0,
      "Hussar": 2500.0,
      "Sanguophage": 6500.0,
      "Neanderthal": 2000.0,
      "Pigskin": 2000.0,
      "Impid": 3000.0,
      "Waster": 2500.0,
      "Yttakin": 2000.0,
      "Highmate": 2000.0,
      "Starjack": 2000.0,
      "EMCM_HereticAstartes": 2000.0,
      "EMCM_HereticAstartes_Khorne": 2000.0,
      "EMCM_HereticAstartes_WorldEaters": 2000.0,
      "EMCM_HereticAstartes_Nurgle": 2000.0,
      "EMCM_HereticAstartes_DeathGuard": 2000.0,
      "EMCM_HereticAstartes_Tzeentch": 2000.0,
      "EMCM_HereticAstartes_ThousandSons": 2000.0,
      "EMCM_HereticAstartes_Slaanesh": 2000.0,
      "EMCM_HereticAstartes_EmperorsChildren": 2000.0,
      "EMCM_HereticAstartes_Undivided": 2000.0,
      "EMCM_HereticAstartes_FallenAngels": 2000.0,
      "EMCM_HereticAstartes_NightLords": 2000.0,
      "EMSM_Astartes": 2000.0,
      "EMSM_Astartes_Salamanders": 2000.0,
      "EMSM_Astartes_ImperialFists": 2000.0,
      "EMSM_Astartes_IronHands": 2000.0,
      "EMSM_Astartes_BlackTemplars": 2000.0,
      "EMSM_Astartes_CrimsonFists": 2000.0,
      "EMSM_Astartes_RavenGuard": 2000.0,
      "EMSM_Astartes_SpaceWolves": 2000.0,
      "EMSM_Astartes_LongFang": 2000.0,
      "EMSM_Astartes_Wulfen": 2000.0,
      "EMSM_Astartes_WhiteScars": 2000.0,
      "EMCH_Poxwalker": 2000.0,
      "EMNC_Necrons": 2000.0,
      "EMOK_Orkz_Grot": 2500.0,
      "EMOK_Orkz_Boyz": 3000.0,
      "EMOK_Orkz_Mek": 3000.0,
      "EMOK_Orkz_Painboy": 3000.0,
      "EMOK_Orkz_Runtherd": 3000.0,
      "EMOK_Orkz_Weirdboy": 3000.0,
      "EMOK_Orkz_Kommando": 3000.0,
      "EMOK_Orkz_Warboss": 3000.0,
      "EMGC_BroodBrothers": 2500.0,
      "EMGC_AcolyteHybrids": 2500.0,
      "EMGC_AcolyteIconward": 6500.0,
      "EMGC_Aberrant": 3000.0,
      "EMGC_AberrantHypermorph": 3000.0,
      "EMGC_NeophyteHybrids": 2500.0,
      "EMGC_Magus": 10000.0,
      "EMGC_PurestrainGenestealer": 11000.0,
      "EMGC_Patriarch": 10500.0,
      "EMAE_Asuryani": 2000.0,
      "EMAE_Exodites": 2000.0,
      "EMTS_Tzaangor": 2000.0,
      "EMTS_TzaangorEnlightened": 2000.0,
      "EMTS_TzaangorShaman": 3000.0
    },
    "EnabledXenotypes": {
      "Baseliner": true,
      "Dirtmole": true,
      "Genie": true,
      "Hussar": true,
      "Sanguophage": true,
      "Neanderthal": true,
      "Pigskin": true,
      "Impid": true,
      "Waster": true,
      "Yttakin": true,
      "Highmate": true,
      "Starjack": true,
      "EMCM_HereticAstartes": true,
      "EMCM_HereticAstartes_Khorne": true,
      "EMCM_HereticAstartes_WorldEaters": true,
      "EMCM_HereticAstartes_Nurgle": true,
      "EMCM_HereticAstartes_DeathGuard": true,
      "EMCM_HereticAstartes_Tzeentch": true,
      "EMCM_HereticAstartes_ThousandSons": true,
      "EMCM_HereticAstartes_Slaanesh": true,
      "EMCM_HereticAstartes_EmperorsChildren": true,
      "EMCM_HereticAstartes_Undivided": true,
      "EMCM_HereticAstartes_FallenAngels": true,
      "EMCM_HereticAstartes_NightLords": true,
      "EMSM_Astartes": true,
      "EMSM_Astartes_Salamanders": true,
      "EMSM_Astartes_ImperialFists": true,
      "EMSM_Astartes_IronHands": true,
      "EMSM_Astartes_BlackTemplars": true,
      "EMSM_Astartes_CrimsonFists": true,
      "EMSM_Astartes_RavenGuard": true,
      "EMSM_Astartes_SpaceWolves": true,
      "EMSM_Astartes_LongFang": true,
      "EMSM_Astartes_Wulfen": true,
      "EMSM_Astartes_WhiteScars": true,
      "EMCH_Poxwalker": true,
      "EMNC_Necrons": true,
      "EMOK_Orkz_Grot": true,
      "EMOK_Orkz_Boyz": true,
      "EMOK_Orkz_Mek": true,
      "EMOK_Orkz_Painboy": true,
      "EMOK_Orkz_Runtherd": true,
      "EMOK_Orkz_Weirdboy": true,
      "EMOK_Orkz_Kommando": true,
      "EMOK_Orkz_Warboss": true,
      "EMGC_BroodBrothers": true,
      "EMGC_AcolyteHybrids": true,
      "EMGC_AcolyteIconward": true,
      "EMGC_Aberrant": true,
      "EMGC_AberrantHypermorph": true,
      "EMGC_NeophyteHybrids": true,
      "EMGC_Magus": true,
      "EMGC_PurestrainGenestealer": true,
      "EMGC_Patriarch": true,
      "EMAE_Asuryani": true,
      "EMAE_Exodites": true,
      "EMTS_Tzaangor": true,
      "EMTS_TzaangorEnlightened": true,
      "EMTS_TzaangorShaman": true
    }
  },
  "EMGC_PatriarchVanillaRace": {
    "DisplayName": "genestealer patriarch",
    "Enabled": true,
    "ModActive": false,
    "BasePrice": 2000,
    "MinAge": 16,
    "MaxAge": 65,
    "AllowCustomXenotypes": true,
    "DefaultXenotype": "Baseliner",
    "PreferredPawnKindDefName": null,
    "AllowedGenders": {
      "AllowMale": true,
      "AllowFemale": true,
      "AllowOther": true
    },
    "XenotypePrices": {
      "Baseliner": 2000.0,
      "Dirtmole": 2000.0,
      "Genie": 2000.0,
      "Hussar": 2500.0,
      "Sanguophage": 6500.0,
      "Neanderthal": 2000.0,
      "Pigskin": 2000.0,
      "Impid": 3000.0,
      "Waster": 2500.0,
      "Yttakin": 2000.0,
      "Highmate": 2000.0,
      "Starjack": 2000.0,
      "EMCM_HereticAstartes": 2000.0,
      "EMCM_HereticAstartes_Khorne": 2000.0,
      "EMCM_HereticAstartes_WorldEaters": 2000.0,
      "EMCM_HereticAstartes_Nurgle": 2000.0,
      "EMCM_HereticAstartes_DeathGuard": 2000.0,
      "EMCM_HereticAstartes_Tzeentch": 2000.0,
      "EMCM_HereticAstartes_ThousandSons": 2000.0,
      "EMCM_HereticAstartes_Slaanesh": 2000.0,
      "EMCM_HereticAstartes_EmperorsChildren": 2000.0,
      "EMCM_HereticAstartes_Undivided": 2000.0,
      "EMCM_HereticAstartes_FallenAngels": 2000.0,
      "EMCM_HereticAstartes_NightLords": 2000.0,
      "EMSM_Astartes": 2000.0,
      "EMSM_Astartes_Salamanders": 2000.0,
      "EMSM_Astartes_ImperialFists": 2000.0,
      "EMSM_Astartes_IronHands": 2000.0,
      "EMSM_Astartes_BlackTemplars": 2000.0,
      "EMSM_Astartes_CrimsonFists": 2000.0,
      "EMSM_Astartes_RavenGuard": 2000.0,
      "EMSM_Astartes_SpaceWolves": 2000.0,
      "EMSM_Astartes_LongFang": 2000.0,
      "EMSM_Astartes_Wulfen": 2000.0,
      "EMSM_Astartes_WhiteScars": 2000.0,
      "EMCH_Poxwalker": 2000.0,
      "EMNC_Necrons": 2000.0,
      "EMOK_Orkz_Grot": 2500.0,
      "EMOK_Orkz_Boyz": 3000.0,
      "EMOK_Orkz_Mek": 3000.0,
      "EMOK_Orkz_Painboy": 3000.0,
      "EMOK_Orkz_Runtherd": 3000.0,
      "EMOK_Orkz_Weirdboy": 3000.0,
      "EMOK_Orkz_Kommando": 3000.0,
      "EMOK_Orkz_Warboss": 3000.0,
      "EMGC_BroodBrothers": 2500.0,
      "EMGC_AcolyteHybrids": 2500.0,
      "EMGC_AcolyteIconward": 6500.0,
      "EMGC_Aberrant": 3000.0,
      "EMGC_AberrantHypermorph": 3000.0,
      "EMGC_NeophyteHybrids": 2500.0,
      "EMGC_Magus": 10000.0,
      "EMGC_PurestrainGenestealer": 11000.0,
      "EMGC_Patriarch": 10500.0,
      "EMAE_Asuryani": 2000.0,
      "EMAE_Exodites": 2000.0,
      "EMTS_Tzaangor": 2000.0,
      "EMTS_TzaangorEnlightened": 2000.0,
      "EMTS_TzaangorShaman": 3000.0
    },
    "EnabledXenotypes": {
      "Baseliner": true,
      "Dirtmole": true,
      "Genie": true,
      "Hussar": true,
      "Sanguophage": true,
      "Neanderthal": true,
      "Pigskin": true,
      "Impid": true,
      "Waster": true,
      "Yttakin": true,
      "Highmate": true,
      "Starjack": true,
      "EMCM_HereticAstartes": true,
      "EMCM_HereticAstartes_Khorne": true,
      "EMCM_HereticAstartes_WorldEaters": true,
      "EMCM_HereticAstartes_Nurgle": true,
      "EMCM_HereticAstartes_DeathGuard": true,
      "EMCM_HereticAstartes_Tzeentch": true,
      "EMCM_HereticAstartes_ThousandSons": true,
      "EMCM_HereticAstartes_Slaanesh": true,
      "EMCM_HereticAstartes_EmperorsChildren": true,
      "EMCM_HereticAstartes_Undivided": true,
      "EMCM_HereticAstartes_FallenAngels": true,
      "EMCM_HereticAstartes_NightLords": true,
      "EMSM_Astartes": true,
      "EMSM_Astartes_Salamanders": true,
      "EMSM_Astartes_ImperialFists": true,
      "EMSM_Astartes_IronHands": true,
      "EMSM_Astartes_BlackTemplars": true,
      "EMSM_Astartes_CrimsonFists": true,
      "EMSM_Astartes_RavenGuard": true,
      "EMSM_Astartes_SpaceWolves": true,
      "EMSM_Astartes_LongFang": true,
      "EMSM_Astartes_Wulfen": true,
      "EMSM_Astartes_WhiteScars": true,
      "EMCH_Poxwalker": true,
      "EMNC_Necrons": true,
      "EMOK_Orkz_Grot": true,
      "EMOK_Orkz_Boyz": true,
      "EMOK_Orkz_Mek": true,
      "EMOK_Orkz_Painboy": true,
      "EMOK_Orkz_Runtherd": true,
      "EMOK_Orkz_Weirdboy": true,
      "EMOK_Orkz_Kommando": true,
      "EMOK_Orkz_Warboss": true,
      "EMGC_BroodBrothers": true,
      "EMGC_AcolyteHybrids": true,
      "EMGC_AcolyteIconward": true,
      "EMGC_Aberrant": true,
      "EMGC_AberrantHypermorph": true,
      "EMGC_NeophyteHybrids": true,
      "EMGC_Magus": true,
      "EMGC_PurestrainGenestealer": true,
      "EMGC_Patriarch": true,
      "EMAE_Asuryani": true,
      "EMAE_Exodites": true,
      "EMTS_Tzaangor": true,
      "EMTS_TzaangorEnlightened": true,
      "EMTS_TzaangorShaman": true
    }
  },
  "EMAE_AsuryaniVanillaRace": {
    "DisplayName": "asuryani",
    "Enabled": true,
    "ModActive": false,
    "BasePrice": 3000,
    "MinAge": 16,
    "MaxAge": 65,
    "AllowCustomXenotypes": true,
    "DefaultXenotype": "Baseliner",
    "PreferredPawnKindDefName": null,
    "AllowedGenders": {
      "AllowMale": true,
      "AllowFemale": true,
      "AllowOther": true
    },
    "XenotypePrices": {
      "Baseliner": 3000.0,
      "Dirtmole": 3000.0,
      "Genie": 3000.0,
      "Hussar": 3750.0,
      "Sanguophage": 9750.0,
      "Neanderthal": 3000.0,
      "Pigskin": 3000.0,
      "Impid": 4500.0,
      "Waster": 3750.0,
      "Yttakin": 3000.0,
      "Highmate": 3000.0,
      "Starjack": 3000.0,
      "EMCM_HereticAstartes": 3000.0,
      "EMCM_HereticAstartes_Khorne": 3000.0,
      "EMCM_HereticAstartes_WorldEaters": 3000.0,
      "EMCM_HereticAstartes_Nurgle": 3000.0,
      "EMCM_HereticAstartes_DeathGuard": 3000.0,
      "EMCM_HereticAstartes_Tzeentch": 3000.0,
      "EMCM_HereticAstartes_ThousandSons": 3000.0,
      "EMCM_HereticAstartes_Slaanesh": 3000.0,
      "EMCM_HereticAstartes_EmperorsChildren": 3000.0,
      "EMCM_HereticAstartes_Undivided": 3000.0,
      "EMCM_HereticAstartes_FallenAngels": 3000.0,
      "EMCM_HereticAstartes_NightLords": 3000.0,
      "EMSM_Astartes": 3000.0,
      "EMSM_Astartes_Salamanders": 3000.0,
      "EMSM_Astartes_ImperialFists": 3000.0,
      "EMSM_Astartes_IronHands": 3000.0,
      "EMSM_Astartes_BlackTemplars": 3000.0,
      "EMSM_Astartes_CrimsonFists": 3000.0,
      "EMSM_Astartes_RavenGuard": 3000.0,
      "EMSM_Astartes_SpaceWolves": 3000.0,
      "EMSM_Astartes_LongFang": 3000.0,
      "EMSM_Astartes_Wulfen": 3000.0,
      "EMSM_Astartes_WhiteScars": 3000.0,
      "EMCH_Poxwalker": 3000.0,
      "EMNC_Necrons": 3000.0,
      "EMOK_Orkz_Grot": 3750.0,
      "EMOK_Orkz_Boyz": 4500.0,
      "EMOK_Orkz_Mek": 4500.0,
      "EMOK_Orkz_Painboy": 4500.0,
      "EMOK_Orkz_Runtherd": 4500.0,
      "EMOK_Orkz_Weirdboy": 4500.0,
      "EMOK_Orkz_Kommando": 4500.0,
      "EMOK_Orkz_Warboss": 4500.0,
      "EMGC_BroodBrothers": 3750.0,
      "EMGC_AcolyteHybrids": 3750.0,
      "EMGC_AcolyteIconward": 9750.0,
      "EMGC_Aberrant": 4500.0,
      "EMGC_AberrantHypermorph": 4500.0,
      "EMGC_NeophyteHybrids": 3750.0,
      "EMGC_Magus": 15000.0,
      "EMGC_PurestrainGenestealer": 16500.0,
      "EMGC_Patriarch": 15750.0,
      "EMAE_Asuryani": 3000.0,
      "EMAE_Exodites": 3000.0,
      "EMTS_Tzaangor": 3000.0,
      "EMTS_TzaangorEnlightened": 3000.0,
      "EMTS_TzaangorShaman": 4500.0
    },
    "EnabledXenotypes": {
      "Baseliner": true,
      "Dirtmole": true,
      "Genie": true,
      "Hussar": true,
      "Sanguophage": true,
      "Neanderthal": true,
      "Pigskin": true,
      "Impid": true,
      "Waster": true,
      "Yttakin": true,
      "Highmate": true,
      "Starjack": true,
      "EMCM_HereticAstartes": true,
      "EMCM_HereticAstartes_Khorne": true,
      "EMCM_HereticAstartes_WorldEaters": true,
      "EMCM_HereticAstartes_Nurgle": true,
      "EMCM_HereticAstartes_DeathGuard": true,
      "EMCM_HereticAstartes_Tzeentch": true,
      "EMCM_HereticAstartes_ThousandSons": true,
      "EMCM_HereticAstartes_Slaanesh": true,
      "EMCM_HereticAstartes_EmperorsChildren": true,
      "EMCM_HereticAstartes_Undivided": true,
      "EMCM_HereticAstartes_FallenAngels": true,
      "EMCM_HereticAstartes_NightLords": true,
      "EMSM_Astartes": true,
      "EMSM_Astartes_Salamanders": true,
      "EMSM_Astartes_ImperialFists": true,
      "EMSM_Astartes_IronHands": true,
      "EMSM_Astartes_BlackTemplars": true,
      "EMSM_Astartes_CrimsonFists": true,
      "EMSM_Astartes_RavenGuard": true,
      "EMSM_Astartes_SpaceWolves": true,
      "EMSM_Astartes_LongFang": true,
      "EMSM_Astartes_Wulfen": true,
      "EMSM_Astartes_WhiteScars": true,
      "EMCH_Poxwalker": true,
      "EMNC_Necrons": true,
      "EMOK_Orkz_Grot": true,
      "EMOK_Orkz_Boyz": true,
      "EMOK_Orkz_Mek": true,
      "EMOK_Orkz_Painboy": true,
      "EMOK_Orkz_Runtherd": true,
      "EMOK_Orkz_Weirdboy": true,
      "EMOK_Orkz_Kommando": true,
      "EMOK_Orkz_Warboss": true,
      "EMGC_BroodBrothers": true,
      "EMGC_AcolyteHybrids": true,
      "EMGC_AcolyteIconward": true,
      "EMGC_Aberrant": true,
      "EMGC_AberrantHypermorph": true,
      "EMGC_NeophyteHybrids": true,
      "EMGC_Magus": true,
      "EMGC_PurestrainGenestealer": true,
      "EMGC_Patriarch": true,
      "EMAE_Asuryani": true,
      "EMAE_Exodites": true,
      "EMTS_Tzaangor": true,
      "EMTS_TzaangorEnlightened": true,
      "EMTS_TzaangorShaman": true
    }
  },
  "EMAE_ExoditeVanillaRace": {
    "DisplayName": "exodite eldar",
    "Enabled": true,
    "ModActive": false,
    "BasePrice": 3000,
    "MinAge": 16,
    "MaxAge": 65,
    "AllowCustomXenotypes": true,
    "DefaultXenotype": "Baseliner",
    "PreferredPawnKindDefName": null,
    "AllowedGenders": {
      "AllowMale": true,
      "AllowFemale": true,
      "AllowOther": true
    },
    "XenotypePrices": {
      "Baseliner": 3000.0,
      "Dirtmole": 3000.0,
      "Genie": 3000.0,
      "Hussar": 3750.0,
      "Sanguophage": 9750.0,
      "Neanderthal": 3000.0,
      "Pigskin": 3000.0,
      "Impid": 4500.0,
      "Waster": 3750.0,
      "Yttakin": 3000.0,
      "Highmate": 3000.0,
      "Starjack": 3000.0,
      "EMCM_HereticAstartes": 3000.0,
      "EMCM_HereticAstartes_Khorne": 3000.0,
      "EMCM_HereticAstartes_WorldEaters": 3000.0,
      "EMCM_HereticAstartes_Nurgle": 3000.0,
      "EMCM_HereticAstartes_DeathGuard": 3000.0,
      "EMCM_HereticAstartes_Tzeentch": 3000.0,
      "EMCM_HereticAstartes_ThousandSons": 3000.0,
      "EMCM_HereticAstartes_Slaanesh": 3000.0,
      "EMCM_HereticAstartes_EmperorsChildren": 3000.0,
      "EMCM_HereticAstartes_Undivided": 3000.0,
      "EMCM_HereticAstartes_FallenAngels": 3000.0,
      "EMCM_HereticAstartes_NightLords": 3000.0,
      "EMSM_Astartes": 3000.0,
      "EMSM_Astartes_Salamanders": 3000.0,
      "EMSM_Astartes_ImperialFists": 3000.0,
      "EMSM_Astartes_IronHands": 3000.0,
      "EMSM_Astartes_BlackTemplars": 3000.0,
      "EMSM_Astartes_CrimsonFists": 3000.0,
      "EMSM_Astartes_RavenGuard": 3000.0,
      "EMSM_Astartes_SpaceWolves": 3000.0,
      "EMSM_Astartes_LongFang": 3000.0,
      "EMSM_Astartes_Wulfen": 3000.0,
      "EMSM_Astartes_WhiteScars": 3000.0,
      "EMCH_Poxwalker": 3000.0,
      "EMNC_Necrons": 3000.0,
      "EMOK_Orkz_Grot": 3750.0,
      "EMOK_Orkz_Boyz": 4500.0,
      "EMOK_Orkz_Mek": 4500.0,
      "EMOK_Orkz_Painboy": 4500.0,
      "EMOK_Orkz_Runtherd": 4500.0,
      "EMOK_Orkz_Weirdboy": 4500.0,
      "EMOK_Orkz_Kommando": 4500.0,
      "EMOK_Orkz_Warboss": 4500.0,
      "EMGC_BroodBrothers": 3750.0,
      "EMGC_AcolyteHybrids": 3750.0,
      "EMGC_AcolyteIconward": 9750.0,
      "EMGC_Aberrant": 4500.0,
      "EMGC_AberrantHypermorph": 4500.0,
      "EMGC_NeophyteHybrids": 3750.0,
      "EMGC_Magus": 15000.0,
      "EMGC_PurestrainGenestealer": 16500.0,
      "EMGC_Patriarch": 15750.0,
      "EMAE_Asuryani": 3000.0,
      "EMAE_Exodites": 3000.0,
      "EMTS_Tzaangor": 3000.0,
      "EMTS_TzaangorEnlightened": 3000.0,
      "EMTS_TzaangorShaman": 4500.0
    },
    "EnabledXenotypes": {
      "Baseliner": true,
      "Dirtmole": true,
      "Genie": true,
      "Hussar": true,
      "Sanguophage": true,
      "Neanderthal": true,
      "Pigskin": true,
      "Impid": true,
      "Waster": true,
      "Yttakin": true,
      "Highmate": true,
      "Starjack": true,
      "EMCM_HereticAstartes": true,
      "EMCM_HereticAstartes_Khorne": true,
      "EMCM_HereticAstartes_WorldEaters": true,
      "EMCM_HereticAstartes_Nurgle": true,
      "EMCM_HereticAstartes_DeathGuard": true,
      "EMCM_HereticAstartes_Tzeentch": true,
      "EMCM_HereticAstartes_ThousandSons": true,
      "EMCM_HereticAstartes_Slaanesh": true,
      "EMCM_HereticAstartes_EmperorsChildren": true,
      "EMCM_HereticAstartes_Undivided": true,
      "EMCM_HereticAstartes_FallenAngels": true,
      "EMCM_HereticAstartes_NightLords": true,
      "EMSM_Astartes": true,
      "EMSM_Astartes_Salamanders": true,
      "EMSM_Astartes_ImperialFists": true,
      "EMSM_Astartes_IronHands": true,
      "EMSM_Astartes_BlackTemplars": true,
      "EMSM_Astartes_CrimsonFists": true,
      "EMSM_Astartes_RavenGuard": true,
      "EMSM_Astartes_SpaceWolves": true,
      "EMSM_Astartes_LongFang": true,
      "EMSM_Astartes_Wulfen": true,
      "EMSM_Astartes_WhiteScars": true,
      "EMCH_Poxwalker": true,
      "EMNC_Necrons": true,
      "EMOK_Orkz_Grot": true,
      "EMOK_Orkz_Boyz": true,
      "EMOK_Orkz_Mek": true,
      "EMOK_Orkz_Painboy": true,
      "EMOK_Orkz_Runtherd": true,
      "EMOK_Orkz_Weirdboy": true,
      "EMOK_Orkz_Kommando": true,
      "EMOK_Orkz_Warboss": true,
      "EMGC_BroodBrothers": true,
      "EMGC_AcolyteHybrids": true,
      "EMGC_AcolyteIconward": true,
      "EMGC_Aberrant": true,
      "EMGC_AberrantHypermorph": true,
      "EMGC_NeophyteHybrids": true,
      "EMGC_Magus": true,
      "EMGC_PurestrainGenestealer": true,
      "EMGC_Patriarch": true,
      "EMAE_Asuryani": true,
      "EMAE_Exodites": true,
      "EMTS_Tzaangor": true,
      "EMTS_TzaangorEnlightened": true,
      "EMTS_TzaangorShaman": true
    }
  },
  "EMAE_DrukhariVanillaRace": {
    "DisplayName": "drukhari",
    "Enabled": true,
    "ModActive": false,
    "BasePrice": 3000,
    "MinAge": 16,
    "MaxAge": 65,
    "AllowCustomXenotypes": true,
    "DefaultXenotype": "Baseliner",
    "PreferredPawnKindDefName": null,
    "AllowedGenders": {
      "AllowMale": true,
      "AllowFemale": true,
      "AllowOther": true
    },
    "XenotypePrices": {
      "Baseliner": 3000.0,
      "Dirtmole": 3000.0,
      "Genie": 3000.0,
      "Hussar": 3750.0,
      "Sanguophage": 9750.0,
      "Neanderthal": 3000.0,
      "Pigskin": 3000.0,
      "Impid": 4500.0,
      "Waster": 3750.0,
      "Yttakin": 3000.0,
      "Highmate": 3000.0,
      "Starjack": 3000.0,
      "EMCM_HereticAstartes": 3000.0,
      "EMCM_HereticAstartes_Khorne": 3000.0,
      "EMCM_HereticAstartes_WorldEaters": 3000.0,
      "EMCM_HereticAstartes_Nurgle": 3000.0,
      "EMCM_HereticAstartes_DeathGuard": 3000.0,
      "EMCM_HereticAstartes_Tzeentch": 3000.0,
      "EMCM_HereticAstartes_ThousandSons": 3000.0,
      "EMCM_HereticAstartes_Slaanesh": 3000.0,
      "EMCM_HereticAstartes_EmperorsChildren": 3000.0,
      "EMCM_HereticAstartes_Undivided": 3000.0,
      "EMCM_HereticAstartes_FallenAngels": 3000.0,
      "EMCM_HereticAstartes_NightLords": 3000.0,
      "EMSM_Astartes": 3000.0,
      "EMSM_Astartes_Salamanders": 3000.0,
      "EMSM_Astartes_ImperialFists": 3000.0,
      "EMSM_Astartes_IronHands": 3000.0,
      "EMSM_Astartes_BlackTemplars": 3000.0,
      "EMSM_Astartes_CrimsonFists": 3000.0,
      "EMSM_Astartes_RavenGuard": 3000.0,
      "EMSM_Astartes_SpaceWolves": 3000.0,
      "EMSM_Astartes_LongFang": 3000.0,
      "EMSM_Astartes_Wulfen": 3000.0,
      "EMSM_Astartes_WhiteScars": 3000.0,
      "EMCH_Poxwalker": 3000.0,
      "EMNC_Necrons": 3000.0,
      "EMOK_Orkz_Grot": 3750.0,
      "EMOK_Orkz_Boyz": 4500.0,
      "EMOK_Orkz_Mek": 4500.0,
      "EMOK_Orkz_Painboy": 4500.0,
      "EMOK_Orkz_Runtherd": 4500.0,
      "EMOK_Orkz_Weirdboy": 4500.0,
      "EMOK_Orkz_Kommando": 4500.0,
      "EMOK_Orkz_Warboss": 4500.0,
      "EMGC_BroodBrothers": 3750.0,
      "EMGC_AcolyteHybrids": 3750.0,
      "EMGC_AcolyteIconward": 9750.0,
      "EMGC_Aberrant": 4500.0,
      "EMGC_AberrantHypermorph": 4500.0,
      "EMGC_NeophyteHybrids": 3750.0,
      "EMGC_Magus": 15000.0,
      "EMGC_PurestrainGenestealer": 16500.0,
      "EMGC_Patriarch": 15750.0,
      "EMAE_Asuryani": 3000.0,
      "EMAE_Exodites": 3000.0,
      "EMTS_Tzaangor": 3000.0,
      "EMTS_TzaangorEnlightened": 3000.0,
      "EMTS_TzaangorShaman": 4500.0
    },
    "EnabledXenotypes": {
      "Baseliner": true,
      "Dirtmole": true,
      "Genie": true,
      "Hussar": true,
      "Sanguophage": true,
      "Neanderthal": true,
      "Pigskin": true,
      "Impid": true,
      "Waster": true,
      "Yttakin": true,
      "Highmate": true,
      "Starjack": true,
      "EMCM_HereticAstartes": true,
      "EMCM_HereticAstartes_Khorne": true,
      "EMCM_HereticAstartes_WorldEaters": true,
      "EMCM_HereticAstartes_Nurgle": true,
      "EMCM_HereticAstartes_DeathGuard": true,
      "EMCM_HereticAstartes_Tzeentch": true,
      "EMCM_HereticAstartes_ThousandSons": true,
      "EMCM_HereticAstartes_Slaanesh": true,
      "EMCM_HereticAstartes_EmperorsChildren": true,
      "EMCM_HereticAstartes_Undivided": true,
      "EMCM_HereticAstartes_FallenAngels": true,
      "EMCM_HereticAstartes_NightLords": true,
      "EMSM_Astartes": true,
      "EMSM_Astartes_Salamanders": true,
      "EMSM_Astartes_ImperialFists": true,
      "EMSM_Astartes_IronHands": true,
      "EMSM_Astartes_BlackTemplars": true,
      "EMSM_Astartes_CrimsonFists": true,
      "EMSM_Astartes_RavenGuard": true,
      "EMSM_Astartes_SpaceWolves": true,
      "EMSM_Astartes_LongFang": true,
      "EMSM_Astartes_Wulfen": true,
      "EMSM_Astartes_WhiteScars": true,
      "EMCH_Poxwalker": true,
      "EMNC_Necrons": true,
      "EMOK_Orkz_Grot": true,
      "EMOK_Orkz_Boyz": true,
      "EMOK_Orkz_Mek": true,
      "EMOK_Orkz_Painboy": true,
      "EMOK_Orkz_Runtherd": true,
      "EMOK_Orkz_Weirdboy": true,
      "EMOK_Orkz_Kommando": true,
      "EMOK_Orkz_Warboss": true,
      "EMGC_BroodBrothers": true,
      "EMGC_AcolyteHybrids": true,
      "EMGC_AcolyteIconward": true,
      "EMGC_Aberrant": true,
      "EMGC_AberrantHypermorph": true,
      "EMGC_NeophyteHybrids": true,
      "EMGC_Magus": true,
      "EMGC_PurestrainGenestealer": true,
      "EMGC_Patriarch": true,
      "EMAE_Asuryani": true,
      "EMAE_Exodites": true,
      "EMTS_Tzaangor": true,
      "EMTS_TzaangorEnlightened": true,
      "EMTS_TzaangorShaman": true
    }
  },
  "EMAE_RillietannVanillaRace": {
    "DisplayName": "rillietann",
    "Enabled": true,
    "ModActive": false,
    "BasePrice": 3000,
    "MinAge": 16,
    "MaxAge": 65,
    "AllowCustomXenotypes": true,
    "DefaultXenotype": "Baseliner",
    "PreferredPawnKindDefName": null,
    "AllowedGenders": {
      "AllowMale": true,
      "AllowFemale": true,
      "AllowOther": true
    },
    "XenotypePrices": {
      "Baseliner": 3000.0,
      "Dirtmole": 3000.0,
      "Genie": 3000.0,
      "Hussar": 3750.0,
      "Sanguophage": 9750.0,
      "Neanderthal": 3000.0,
      "Pigskin": 3000.0,
      "Impid": 4500.0,
      "Waster": 3750.0,
      "Yttakin": 3000.0,
      "Highmate": 3000.0,
      "Starjack": 3000.0,
      "EMCM_HereticAstartes": 3000.0,
      "EMCM_HereticAstartes_Khorne": 3000.0,
      "EMCM_HereticAstartes_WorldEaters": 3000.0,
      "EMCM_HereticAstartes_Nurgle": 3000.0,
      "EMCM_HereticAstartes_DeathGuard": 3000.0,
      "EMCM_HereticAstartes_Tzeentch": 3000.0,
      "EMCM_HereticAstartes_ThousandSons": 3000.0,
      "EMCM_HereticAstartes_Slaanesh": 3000.0,
      "EMCM_HereticAstartes_EmperorsChildren": 3000.0,
      "EMCM_HereticAstartes_Undivided": 3000.0,
      "EMCM_HereticAstartes_FallenAngels": 3000.0,
      "EMCM_HereticAstartes_NightLords": 3000.0,
      "EMSM_Astartes": 3000.0,
      "EMSM_Astartes_Salamanders": 3000.0,
      "EMSM_Astartes_ImperialFists": 3000.0,
      "EMSM_Astartes_IronHands": 3000.0,
      "EMSM_Astartes_BlackTemplars": 3000.0,
      "EMSM_Astartes_CrimsonFists": 3000.0,
      "EMSM_Astartes_RavenGuard": 3000.0,
      "EMSM_Astartes_SpaceWolves": 3000.0,
      "EMSM_Astartes_LongFang": 3000.0,
      "EMSM_Astartes_Wulfen": 3000.0,
      "EMSM_Astartes_WhiteScars": 3000.0,
      "EMCH_Poxwalker": 3000.0,
      "EMNC_Necrons": 3000.0,
      "EMOK_Orkz_Grot": 3750.0,
      "EMOK_Orkz_Boyz": 4500.0,
      "EMOK_Orkz_Mek": 4500.0,
      "EMOK_Orkz_Painboy": 4500.0,
      "EMOK_Orkz_Runtherd": 4500.0,
      "EMOK_Orkz_Weirdboy": 4500.0,
      "EMOK_Orkz_Kommando": 4500.0,
      "EMOK_Orkz_Warboss": 4500.0,
      "EMGC_BroodBrothers": 3750.0,
      "EMGC_AcolyteHybrids": 3750.0,
      "EMGC_AcolyteIconward": 9750.0,
      "EMGC_Aberrant": 4500.0,
      "EMGC_AberrantHypermorph": 4500.0,
      "EMGC_NeophyteHybrids": 3750.0,
      "EMGC_Magus": 15000.0,
      "EMGC_PurestrainGenestealer": 16500.0,
      "EMGC_Patriarch": 15750.0,
      "EMAE_Asuryani": 3000.0,
      "EMAE_Exodites": 3000.0,
      "EMTS_Tzaangor": 3000.0,
      "EMTS_TzaangorEnlightened": 3000.0,
      "EMTS_TzaangorShaman": 4500.0
    },
    "EnabledXenotypes": {
      "Baseliner": true,
      "Dirtmole": true,
      "Genie": true,
      "Hussar": true,
      "Sanguophage": true,
      "Neanderthal": true,
      "Pigskin": true,
      "Impid": true,
      "Waster": true,
      "Yttakin": true,
      "Highmate": true,
      "Starjack": true,
      "EMCM_HereticAstartes": true,
      "EMCM_HereticAstartes_Khorne": true,
      "EMCM_HereticAstartes_WorldEaters": true,
      "EMCM_HereticAstartes_Nurgle": true,
      "EMCM_HereticAstartes_DeathGuard": true,
      "EMCM_HereticAstartes_Tzeentch": true,
      "EMCM_HereticAstartes_ThousandSons": true,
      "EMCM_HereticAstartes_Slaanesh": true,
      "EMCM_HereticAstartes_EmperorsChildren": true,
      "EMCM_HereticAstartes_Undivided": true,
      "EMCM_HereticAstartes_FallenAngels": true,
      "EMCM_HereticAstartes_NightLords": true,
      "EMSM_Astartes": true,
      "EMSM_Astartes_Salamanders": true,
      "EMSM_Astartes_ImperialFists": true,
      "EMSM_Astartes_IronHands": true,
      "EMSM_Astartes_BlackTemplars": true,
      "EMSM_Astartes_CrimsonFists": true,
      "EMSM_Astartes_RavenGuard": true,
      "EMSM_Astartes_SpaceWolves": true,
      "EMSM_Astartes_LongFang": true,
      "EMSM_Astartes_Wulfen": true,
      "EMSM_Astartes_WhiteScars": true,
      "EMCH_Poxwalker": true,
      "EMNC_Necrons": true,
      "EMOK_Orkz_Grot": true,
      "EMOK_Orkz_Boyz": true,
      "EMOK_Orkz_Mek": true,
      "EMOK_Orkz_Painboy": true,
      "EMOK_Orkz_Runtherd": true,
      "EMOK_Orkz_Weirdboy": true,
      "EMOK_Orkz_Kommando": true,
      "EMOK_Orkz_Warboss": true,
      "EMGC_BroodBrothers": true,
      "EMGC_AcolyteHybrids": true,
      "EMGC_AcolyteIconward": true,
      "EMGC_Aberrant": true,
      "EMGC_AberrantHypermorph": true,
      "EMGC_NeophyteHybrids": true,
      "EMGC_Magus": true,
      "EMGC_PurestrainGenestealer": true,
      "EMGC_Patriarch": true,
      "EMAE_Asuryani": true,
      "EMAE_Exodites": true,
      "EMTS_Tzaangor": true,
      "EMTS_TzaangorEnlightened": true,
      "EMTS_TzaangorShaman": true
    }
  }
}